{
"meta":{"test_sets":[],"test_metrics":[],"learn_metrics":[{"best_value":"Min","name":"RMSE"}],"launch_mode":"Train","parameters":"","iteration_count":1000,"learn_sets":["learn"],"name":"experiment"},
"iterations":[
{"learn":[14.61268541],"iteration":0,"passed_time":0.1385336608,"remaining_time":138.3951271},
{"learn":[14.23196558],"iteration":1,"passed_time":0.1415054534,"remaining_time":70.61122126},
{"learn":[13.86674177],"iteration":2,"passed_time":0.1442889615,"remaining_time":47.95203152},
{"learn":[13.49946468],"iteration":3,"passed_time":0.147097884,"remaining_time":36.62737311},
{"learn":[13.16661202],"iteration":4,"passed_time":0.1498373249,"remaining_time":29.81762766},
{"learn":[12.85632158],"iteration":5,"passed_time":0.1526575929,"remaining_time":25.29027456},
{"learn":[12.56784336],"iteration":6,"passed_time":0.1554152877,"remaining_time":22.04676867},
{"learn":[12.31617801],"iteration":7,"passed_time":0.157265831,"remaining_time":19.50096305},
{"learn":[12.01509946],"iteration":8,"passed_time":0.1579117073,"remaining_time":17.38783354},
{"learn":[11.71512571],"iteration":9,"passed_time":0.1584434016,"remaining_time":15.68589675},
{"learn":[11.43264457],"iteration":10,"passed_time":0.1590043301,"remaining_time":14.29593477},
{"learn":[11.17973129],"iteration":11,"passed_time":0.1595555656,"remaining_time":13.13674157},
{"learn":[10.93746433],"iteration":12,"passed_time":0.1600754333,"remaining_time":12.15341944},
{"learn":[10.69387075],"iteration":13,"passed_time":0.160599019,"remaining_time":11.31075948},
{"learn":[10.4615922],"iteration":14,"passed_time":0.1611302329,"remaining_time":10.5808853},
{"learn":[10.2299235],"iteration":15,"passed_time":0.1616676364,"remaining_time":9.942559637},
{"learn":[10.01419731],"iteration":16,"passed_time":0.1622181353,"remaining_time":9.38002512},
{"learn":[9.795856918],"iteration":17,"passed_time":0.1627412679,"remaining_time":8.878440284},
{"learn":[9.60040151],"iteration":18,"passed_time":0.1632796857,"remaining_time":8.430387984},
{"learn":[9.418664989],"iteration":19,"passed_time":0.1638925181,"remaining_time":8.030733385},
{"learn":[9.249278645],"iteration":20,"passed_time":0.1644346899,"remaining_time":7.665788639},
{"learn":[9.090113396],"iteration":21,"passed_time":0.164973215,"remaining_time":7.333809284},
{"learn":[8.909548708],"iteration":22,"passed_time":0.165519851,"remaining_time":7.030995411},
{"learn":[8.740140208],"iteration":23,"passed_time":0.1660444463,"remaining_time":6.75247415},
{"learn":[8.59377682],"iteration":24,"passed_time":0.1665878935,"remaining_time":6.496927848},
{"learn":[8.453885414],"iteration":25,"passed_time":0.1671302455,"remaining_time":6.260956121},
{"learn":[8.317732234],"iteration":26,"passed_time":0.1676686793,"remaining_time":6.042282407},
{"learn":[8.180896085],"iteration":27,"passed_time":0.16820925,"remaining_time":5.839263963},
{"learn":[8.053220863],"iteration":28,"passed_time":0.168736954,"remaining_time":5.649778702},
{"learn":[7.924234474],"iteration":29,"passed_time":0.1692706875,"remaining_time":5.473085561},
{"learn":[7.818879511],"iteration":30,"passed_time":0.1698286729,"remaining_time":5.308515615},
{"learn":[7.719346395],"iteration":31,"passed_time":0.1703612783,"remaining_time":5.153428669},
{"learn":[7.624163594],"iteration":32,"passed_time":0.1708986313,"remaining_time":5.007847771},
{"learn":[7.524952543],"iteration":33,"passed_time":0.1714349923,"remaining_time":4.870770664},
{"learn":[7.424464745],"iteration":34,"passed_time":0.1719714895,"remaining_time":4.741499638},
{"learn":[7.327482321],"iteration":35,"passed_time":0.1725019004,"remaining_time":4.619217555},
{"learn":[7.238666841],"iteration":36,"passed_time":0.1730420027,"remaining_time":4.50376888},
{"learn":[7.158842395],"iteration":37,"passed_time":0.1735910998,"remaining_time":4.394595736},
{"learn":[7.074348246],"iteration":38,"passed_time":0.1741254729,"remaining_time":4.290630242},
{"learn":[6.992269093],"iteration":39,"passed_time":0.1746546317,"remaining_time":4.19171116},
{"learn":[6.925219745],"iteration":40,"passed_time":0.1752000059,"remaining_time":4.097970871},
{"learn":[6.86013671],"iteration":41,"passed_time":0.1757452713,"remaining_time":4.008665951},
{"learn":[6.786739622],"iteration":42,"passed_time":0.1762687378,"remaining_time":3.923004234},
{"learn":[6.73057926],"iteration":43,"passed_time":0.1768007707,"remaining_time":3.841398564},
{"learn":[6.666356486],"iteration":44,"passed_time":0.1773284396,"remaining_time":3.76330355},
{"learn":[6.606182832],"iteration":45,"passed_time":0.1778600906,"remaining_time":3.688663618},
{"learn":[6.547854615],"iteration":46,"passed_time":0.1783879404,"remaining_time":3.617100153},
{"learn":[6.49240675],"iteration":47,"passed_time":0.1789447009,"remaining_time":3.549069901},
{"learn":[6.431317261],"iteration":48,"passed_time":0.1794875973,"remaining_time":3.483524593},
{"learn":[6.377586395],"iteration":49,"passed_time":0.1799924776,"remaining_time":3.419857075},
{"learn":[6.327558015],"iteration":50,"passed_time":0.1805238685,"remaining_time":3.359159827},
{"learn":[6.282040317],"iteration":51,"passed_time":0.1810643951,"remaining_time":3.300943203},
{"learn":[6.237655841],"iteration":52,"passed_time":0.1816029058,"remaining_time":3.244867014},
{"learn":[6.192792003],"iteration":53,"passed_time":0.1821328019,"remaining_time":3.190696862},
{"learn":[6.150579347],"iteration":54,"passed_time":0.1826785925,"remaining_time":3.138750362},
{"learn":[6.115693845],"iteration":55,"passed_time":0.1832266736,"remaining_time":3.088678212},
{"learn":[6.078780782],"iteration":56,"passed_time":0.1837544457,"remaining_time":3.04000776},
{"learn":[6.045146957],"iteration":57,"passed_time":0.1842914721,"remaining_time":2.993147701},
{"learn":[6.008080327],"iteration":58,"passed_time":0.1848107745,"remaining_time":2.947575235},
{"learn":[5.977575734],"iteration":59,"passed_time":0.1853299489,"remaining_time":2.903502533},
{"learn":[5.948036502],"iteration":60,"passed_time":0.1858577194,"remaining_time":2.86099014},
{"learn":[5.914888282],"iteration":61,"passed_time":0.1863928699,"remaining_time":2.819943742},
{"learn":[5.884957796],"iteration":62,"passed_time":0.1869225011,"remaining_time":2.780101325},
{"learn":[5.849539885],"iteration":63,"passed_time":0.1874550192,"remaining_time":2.741529655},
{"learn":[5.821387627],"iteration":64,"passed_time":0.188127203,"remaining_time":2.706137458},
{"learn":[5.797012279],"iteration":65,"passed_time":0.1887979181,"remaining_time":2.671776598},
{"learn":[5.768685095],"iteration":66,"passed_time":0.1894638479,"remaining_time":2.638354778},
{"learn":[5.755484587],"iteration":67,"passed_time":0.1897719716,"remaining_time":2.600992317},
{"learn":[5.731887055],"iteration":68,"passed_time":0.1904048508,"remaining_time":2.56908574},
{"learn":[5.707148487],"iteration":69,"passed_time":0.1910117526,"remaining_time":2.53772757},
{"learn":[5.685365039],"iteration":70,"passed_time":0.1915660088,"remaining_time":2.506546791},
{"learn":[5.663541834],"iteration":71,"passed_time":0.1920991002,"remaining_time":2.475943957},
{"learn":[5.638108797],"iteration":72,"passed_time":0.1926267578,"remaining_time":2.446095951},
{"learn":[5.619204893],"iteration":73,"passed_time":0.1931383848,"remaining_time":2.416839788},
{"learn":[5.598472793],"iteration":74,"passed_time":0.1936540269,"remaining_time":2.388399665},
{"learn":[5.577007075],"iteration":75,"passed_time":0.1942003043,"remaining_time":2.361066857},
{"learn":[5.562637084],"iteration":76,"passed_time":0.1947284383,"remaining_time":2.334212318},
{"learn":[5.54729991],"iteration":77,"passed_time":0.1952442509,"remaining_time":2.307887171},
{"learn":[5.530737623],"iteration":78,"passed_time":0.1957781773,"remaining_time":2.282426598},
{"learn":[5.513704873],"iteration":79,"passed_time":0.1963031096,"remaining_time":2.257485761},
{"learn":[5.501575529],"iteration":80,"passed_time":0.196834061,"remaining_time":2.233216074},
{"learn":[5.484080734],"iteration":81,"passed_time":0.1973687399,"remaining_time":2.209567113},
{"learn":[5.472178894],"iteration":82,"passed_time":0.1979064876,"remaining_time":2.186509026},
{"learn":[5.458923342],"iteration":83,"passed_time":0.1984545371,"remaining_time":2.164099476},
{"learn":[5.451382371],"iteration":84,"passed_time":0.1988117797,"remaining_time":2.140150334},
{"learn":[5.441410748],"iteration":85,"passed_time":0.1993478141,"remaining_time":2.118650024},
{"learn":[5.434047468],"iteration":86,"passed_time":0.1997061343,"remaining_time":2.095766673},
{"learn":[5.422107497],"iteration":87,"passed_time":0.2002871164,"remaining_time":2.075702843},
{"learn":[5.40731265],"iteration":88,"passed_time":0.2008271546,"remaining_time":2.055657729},
{"learn":[5.396360181],"iteration":89,"passed_time":0.201360808,"remaining_time":2.035981503},
{"learn":[5.383793239],"iteration":90,"passed_time":0.2018743581,"remaining_time":2.016525182},
{"learn":[5.369605034],"iteration":91,"passed_time":0.20259188,"remaining_time":1.999493772},
{"learn":[5.357467333],"iteration":92,"passed_time":0.2032129013,"remaining_time":1.981872059},
{"learn":[5.341109968],"iteration":93,"passed_time":0.203883622,"remaining_time":1.96509108},
{"learn":[5.330529276],"iteration":94,"passed_time":0.2044408581,"remaining_time":1.947568174},
{"learn":[5.319862075],"iteration":95,"passed_time":0.2049692771,"remaining_time":1.930127359},
{"learn":[5.313052243],"iteration":96,"passed_time":0.2054749244,"remaining_time":1.912823265},
{"learn":[5.299677207],"iteration":97,"passed_time":0.2060191738,"remaining_time":1.896217294},
{"learn":[5.287546698],"iteration":98,"passed_time":0.2065590111,"remaining_time":1.879895646},
{"learn":[5.279803754],"iteration":99,"passed_time":0.2071053789,"remaining_time":1.86394841},
{"learn":[5.272254612],"iteration":100,"passed_time":0.2076531935,"remaining_time":1.848319019},
{"learn":[5.268813888],"iteration":101,"passed_time":0.2079182348,"remaining_time":1.830495832},
{"learn":[5.258113767],"iteration":102,"passed_time":0.2084534834,"remaining_time":1.815366744},
{"learn":[5.251018576],"iteration":103,"passed_time":0.2089862481,"remaining_time":1.800496907},
{"learn":[5.24171237],"iteration":104,"passed_time":0.2095370045,"remaining_time":1.786053514},
{"learn":[5.233984943],"iteration":105,"passed_time":0.2101704408,"remaining_time":1.772569567},
{"learn":[5.226240449],"iteration":106,"passed_time":0.2108081837,"remaining_time":1.759361757},
{"learn":[5.220541644],"iteration":107,"passed_time":0.2113715973,"remaining_time":1.745772822},
{"learn":[5.211712096],"iteration":108,"passed_time":0.2119043131,"remaining_time":1.732171954},
{"learn":[5.203388597],"iteration":109,"passed_time":0.2124352989,"remaining_time":1.718794691},
{"learn":[5.196026544],"iteration":110,"passed_time":0.2129901892,"remaining_time":1.705840344},
{"learn":[5.188716772],"iteration":111,"passed_time":0.2135514692,"remaining_time":1.693158077},
{"learn":[5.182163132],"iteration":112,"passed_time":0.2140601516,"remaining_time":1.680277473},
{"learn":[5.17764747],"iteration":113,"passed_time":0.2145915032,"remaining_time":1.667790104},
{"learn":[5.170548056],"iteration":114,"passed_time":0.2151376216,"remaining_time":1.655624306},
{"learn":[5.165901827],"iteration":115,"passed_time":0.2155834995,"remaining_time":1.642894945},
{"learn":[5.160333668],"iteration":116,"passed_time":0.2161719998,"remaining_time":1.63145193},
{"learn":[5.148953243],"iteration":117,"passed_time":0.2167118803,"remaining_time":1.619829478},
{"learn":[5.144729126],"iteration":118,"passed_time":0.2171450453,"remaining_time":1.607603235},
{"learn":[5.139939946],"iteration":119,"passed_time":0.217678549,"remaining_time":1.596309359},
{"learn":[5.132898872],"iteration":120,"passed_time":0.2181999194,"remaining_time":1.5851052},
{"learn":[5.129073077],"iteration":121,"passed_time":0.2187413651,"remaining_time":1.574220644},
{"learn":[5.127123916],"iteration":122,"passed_time":0.2190264913,"remaining_time":1.56167669},
{"learn":[5.121282057],"iteration":123,"passed_time":0.2195763891,"remaining_time":1.551200942},
{"learn":[5.114489821],"iteration":124,"passed_time":0.2201119471,"remaining_time":1.54078363},
{"learn":[5.107777291],"iteration":125,"passed_time":0.2206525898,"remaining_time":1.53055844},
{"learn":[5.103518754],"iteration":126,"passed_time":0.2211935543,"remaining_time":1.520487976},
{"learn":[5.101133351],"iteration":127,"passed_time":0.2215275096,"remaining_time":1.509156159},
{"learn":[5.096462705],"iteration":128,"passed_time":0.2220637553,"remaining_time":1.499360705},
{"learn":[5.08562082],"iteration":129,"passed_time":0.2226087029,"remaining_time":1.489765935},
{"learn":[5.080483682],"iteration":130,"passed_time":0.2231684129,"remaining_time":1.480407258},
{"learn":[5.07437499],"iteration":131,"passed_time":0.2237130097,"remaining_time":1.471082519},
{"learn":[5.070683732],"iteration":132,"passed_time":0.2242629219,"remaining_time":1.461924461},
{"learn":[5.06432037],"iteration":133,"passed_time":0.2248177081,"remaining_time":1.452926382},
{"learn":[5.057436484],"iteration":134,"passed_time":0.2253553285,"remaining_time":1.443943401},
{"learn":[5.053254656],"iteration":135,"passed_time":0.2258952274,"remaining_time":1.435099092},
{"learn":[5.04801663],"iteration":136,"passed_time":0.2264461011,"remaining_time":1.426445148},
{"learn":[5.045680836],"iteration":137,"passed_time":0.2268793926,"remaining_time":1.417174177},
{"learn":[5.041857933],"iteration":138,"passed_time":0.2274161508,"remaining_time":1.408671265},
{"learn":[5.035264888],"iteration":139,"passed_time":0.2279539193,"remaining_time":1.400288361},
{"learn":[5.028771948],"iteration":140,"passed_time":0.2284688512,"remaining_time":1.391877611},
{"learn":[5.024912247],"iteration":141,"passed_time":0.2290025302,"remaining_time":1.383691344},
{"learn":[5.02239068],"iteration":142,"passed_time":0.2295250655,"remaining_time":1.375545323},
{"learn":[5.017110572],"iteration":143,"passed_time":0.2300476521,"remaining_time":1.367505488},
{"learn":[5.010707886],"iteration":144,"passed_time":0.230586997,"remaining_time":1.359668155},
{"learn":[5.004389868],"iteration":145,"passed_time":0.2311206392,"remaining_time":1.351897437},
{"learn":[4.997628683],"iteration":146,"passed_time":0.2316483064,"remaining_time":1.344190513},
{"learn":[4.991497851],"iteration":147,"passed_time":0.2321867979,"remaining_time":1.336642917},
{"learn":[4.988345253],"iteration":148,"passed_time":0.2327270074,"remaining_time":1.329199217},
{"learn":[4.98460423],"iteration":149,"passed_time":0.233256689,"remaining_time":1.321787904},
{"learn":[4.982441783],"iteration":150,"passed_time":0.2338696826,"remaining_time":1.314936163},
{"learn":[4.977461771],"iteration":151,"passed_time":0.2344805066,"remaining_time":1.308154405},
{"learn":[4.973601586],"iteration":152,"passed_time":0.2351628866,"remaining_time":1.301849444},
{"learn":[4.968328804],"iteration":153,"passed_time":0.235763233,"remaining_time":1.295166852},
{"learn":[4.9640736],"iteration":154,"passed_time":0.2363339706,"remaining_time":1.288401323},
{"learn":[4.960865882],"iteration":155,"passed_time":0.2368433927,"remaining_time":1.281383484},
{"learn":[4.957014156],"iteration":156,"passed_time":0.2373856895,"remaining_time":1.274625072},
{"learn":[4.952244852],"iteration":157,"passed_time":0.2379144664,"remaining_time":1.267873295},
{"learn":[4.949695675],"iteration":158,"passed_time":0.2384430703,"remaining_time":1.261198881},
{"learn":[4.946584698],"iteration":159,"passed_time":0.2389790695,"remaining_time":1.254640115},
{"learn":[4.940192834],"iteration":160,"passed_time":0.2395364216,"remaining_time":1.248267439},
{"learn":[4.936727994],"iteration":161,"passed_time":0.2400891287,"remaining_time":1.24194253},
{"learn":[4.932342063],"iteration":162,"passed_time":0.2406331636,"remaining_time":1.235643913},
{"learn":[4.925830838],"iteration":163,"passed_time":0.2411685655,"remaining_time":1.229371468},
{"learn":[4.922571773],"iteration":164,"passed_time":0.2417106925,"remaining_time":1.223202595},
{"learn":[4.918395814],"iteration":165,"passed_time":0.2422366008,"remaining_time":1.21702003},
{"learn":[4.911142452],"iteration":166,"passed_time":0.2427688923,"remaining_time":1.21093705},
{"learn":[4.908276131],"iteration":167,"passed_time":0.2432757101,"remaining_time":1.204793993},
{"learn":[4.904584645],"iteration":168,"passed_time":0.2438087911,"remaining_time":1.198846777},
{"learn":[4.89795517],"iteration":169,"passed_time":0.2443415638,"remaining_time":1.192961752},
{"learn":[4.895556491],"iteration":170,"passed_time":0.2449415243,"remaining_time":1.187465051},
{"learn":[4.890591233],"iteration":171,"passed_time":0.2454815097,"remaining_time":1.18173657},
{"learn":[4.884629277],"iteration":172,"passed_time":0.2460206104,"remaining_time":1.176063843},
{"learn":[4.880550786],"iteration":173,"passed_time":0.2465367769,"remaining_time":1.170341251},
{"learn":[4.876384842],"iteration":174,"passed_time":0.2470770121,"remaining_time":1.164791628},
{"learn":[4.872638238],"iteration":175,"passed_time":0.2476070683,"remaining_time":1.159251274},
{"learn":[4.869137118],"iteration":176,"passed_time":0.2481486321,"remaining_time":1.153821041},
{"learn":[4.863587157],"iteration":177,"passed_time":0.2488028122,"remaining_time":1.148965796},
{"learn":[4.858028614],"iteration":178,"passed_time":0.2494672954,"remaining_time":1.144204746},
{"learn":[4.853838176],"iteration":179,"passed_time":0.2501374925,"remaining_time":1.139515244},
{"learn":[4.853462329],"iteration":180,"passed_time":0.2504446907,"remaining_time":1.133227633},
{"learn":[4.851573196],"iteration":181,"passed_time":0.2509668169,"remaining_time":1.127971737},
{"learn":[4.848442087],"iteration":182,"passed_time":0.2515076653,"remaining_time":1.122851162},
{"learn":[4.845547104],"iteration":183,"passed_time":0.2520615317,"remaining_time":1.117838097},
{"learn":[4.839868817],"iteration":184,"passed_time":0.2525916439,"remaining_time":1.112768594},
{"learn":[4.836336958],"iteration":185,"passed_time":0.2531331609,"remaining_time":1.107797812},
{"learn":[4.831124789],"iteration":186,"passed_time":0.2536469344,"remaining_time":1.102753784},
{"learn":[4.827407333],"iteration":187,"passed_time":0.2541947593,"remaining_time":1.097905024},
{"learn":[4.824088918],"iteration":188,"passed_time":0.2547272606,"remaining_time":1.093036023},
{"learn":[4.820934539],"iteration":189,"passed_time":0.2552538951,"remaining_time":1.088187658},
{"learn":[4.816975227],"iteration":190,"passed_time":0.2557710543,"remaining_time":1.083344413},
{"learn":[4.812340486],"iteration":191,"passed_time":0.2562844043,"remaining_time":1.078530201},
{"learn":[4.806402747],"iteration":192,"passed_time":0.2568043969,"remaining_time":1.073788333},
{"learn":[4.801521788],"iteration":193,"passed_time":0.2573820673,"remaining_time":1.06932962},
{"learn":[4.797601172],"iteration":194,"passed_time":0.257967833,"remaining_time":1.064944131},
{"learn":[4.792694629],"iteration":195,"passed_time":0.2586308055,"remaining_time":1.06091412},
{"learn":[4.789794613],"iteration":196,"passed_time":0.2592360344,"remaining_time":1.056682922},
{"learn":[4.785367055],"iteration":197,"passed_time":0.2597574441,"remaining_time":1.052148839},
{"learn":[4.780376856],"iteration":198,"passed_time":0.2603113577,"remaining_time":1.047785917},
{"learn":[4.776691261],"iteration":199,"passed_time":0.260835439,"remaining_time":1.043341756},
{"learn":[4.773470753],"iteration":200,"passed_time":0.2613799198,"remaining_time":1.039017691},
{"learn":[4.77207327],"iteration":201,"passed_time":0.261903146,"remaining_time":1.034647082},
{"learn":[4.767347177],"iteration":202,"passed_time":0.2624290039,"remaining_time":1.03032471},
{"learn":[4.763983068],"iteration":203,"passed_time":0.2629693639,"remaining_time":1.026096146},
{"learn":[4.761588849],"iteration":204,"passed_time":0.2634773899,"remaining_time":1.02177817},
{"learn":[4.758558086],"iteration":205,"passed_time":0.2640184036,"remaining_time":1.017624332},
{"learn":[4.753678804],"iteration":206,"passed_time":0.2646498409,"remaining_time":1.013851806},
{"learn":[4.746510889],"iteration":207,"passed_time":0.2653045102,"remaining_time":1.010197943},
{"learn":[4.744840601],"iteration":208,"passed_time":0.2659258358,"remaining_time":1.006446584},
{"learn":[4.741702222],"iteration":209,"passed_time":0.266569122,"remaining_time":1.00280765},
{"learn":[4.739352853],"iteration":210,"passed_time":0.2670785218,"remaining_time":0.9986964629},
{"learn":[4.735539287],"iteration":211,"passed_time":0.267596962,"remaining_time":0.9946528587},
{"learn":[4.730726751],"iteration":212,"passed_time":0.2681339243,"remaining_time":0.9907107907},
{"learn":[4.726416092],"iteration":213,"passed_time":0.2686610751,"remaining_time":0.9867645096},
{"learn":[4.721293082],"iteration":214,"passed_time":0.2691856336,"remaining_time":0.9828405692},
{"learn":[4.718443695],"iteration":215,"passed_time":0.2696948468,"remaining_time":0.9788924069},
{"learn":[4.711627962],"iteration":216,"passed_time":0.2702383965,"remaining_time":0.9750998362},
{"learn":[4.709790764],"iteration":217,"passed_time":0.2707560049,"remaining_time":0.9712440176},
{"learn":[4.706913073],"iteration":218,"passed_time":0.2712820029,"remaining_time":0.9674486038},
{"learn":[4.703846389],"iteration":219,"passed_time":0.2718120751,"remaining_time":0.9636973572},
{"learn":[4.701001135],"iteration":220,"passed_time":0.2723787748,"remaining_time":0.9601043691},
{"learn":[4.700380864],"iteration":221,"passed_time":0.272988052,"remaining_time":0.956687858},
{"learn":[4.695837486],"iteration":222,"passed_time":0.2736326473,"remaining_time":0.9534195826},
{"learn":[4.691242996],"iteration":223,"passed_time":0.2742743988,"remaining_time":0.9501648814},
{"learn":[4.690284609],"iteration":224,"passed_time":0.2748742072,"remaining_time":0.9467889359},
{"learn":[4.68827119],"iteration":225,"passed_time":0.2753792548,"remaining_time":0.9431130232},
{"learn":[4.686922425],"iteration":226,"passed_time":0.2758954902,"remaining_time":0.939503145},
{"learn":[4.686085874],"iteration":227,"passed_time":0.2763953891,"remaining_time":0.9358650895},
{"learn":[4.683230741],"iteration":228,"passed_time":0.2769160863,"remaining_time":0.9323244651},
{"learn":[4.6773487],"iteration":229,"passed_time":0.2774817171,"remaining_time":0.9289605313},
{"learn":[4.671462906],"iteration":230,"passed_time":0.2780063981,"remaining_time":0.9254845027},
{"learn":[4.664799601],"iteration":231,"passed_time":0.2785485876,"remaining_time":0.922091876},
{"learn":[4.660979386],"iteration":232,"passed_time":0.2790815828,"remaining_time":0.9186934508},
{"learn":[4.656281279],"iteration":233,"passed_time":0.2796132307,"remaining_time":0.9153151056},
{"learn":[4.651997094],"iteration":234,"passed_time":0.2801461803,"remaining_time":0.9119652253},
{"learn":[4.650151977],"iteration":235,"passed_time":0.2806576945,"remaining_time":0.9085698245},
{"learn":[4.648478046],"iteration":236,"passed_time":0.2811717306,"remaining_time":0.9052068794},
{"learn":[4.646364602],"iteration":237,"passed_time":0.2817037723,"remaining_time":0.9019255231},
{"learn":[4.642635873],"iteration":238,"passed_time":0.2822395057,"remaining_time":0.8986789281},
{"learn":[4.640860821],"iteration":239,"passed_time":0.2827522376,"remaining_time":0.8953820856},
{"learn":[4.639446822],"iteration":240,"passed_time":0.2832621833,"remaining_time":0.8920995732},
{"learn":[4.637120072],"iteration":241,"passed_time":0.2837956782,"remaining_time":0.8889137358},
{"learn":[4.633769267],"iteration":242,"passed_time":0.2843240131,"remaining_time":0.8857336541},
{"learn":[4.630491517],"iteration":243,"passed_time":0.2848482874,"remaining_time":0.8825627265},
{"learn":[4.627813333],"iteration":244,"passed_time":0.2853536497,"remaining_time":0.8793551245},
{"learn":[4.622496304],"iteration":245,"passed_time":0.2858881773,"remaining_time":0.8762588849},
{"learn":[4.618979301],"iteration":246,"passed_time":0.2864411906,"remaining_time":0.873239743},
{"learn":[4.616563458],"iteration":247,"passed_time":0.2870061762,"remaining_time":0.8702767923},
{"learn":[4.614759385],"iteration":248,"passed_time":0.2875421849,"remaining_time":0.8672457064},
{"learn":[4.61251363],"iteration":249,"passed_time":0.2880583138,"remaining_time":0.8641749414},
{"learn":[4.608796693],"iteration":250,"passed_time":0.2885937181,"remaining_time":0.8611820513},
{"learn":[4.60847774],"iteration":251,"passed_time":0.2891190948,"remaining_time":0.8581789004},
{"learn":[4.605195659],"iteration":252,"passed_time":0.2896195149,"remaining_time":0.8551216508},
{"learn":[4.60103766],"iteration":253,"passed_time":0.2901601448,"remaining_time":0.85220263},
{"learn":[4.599325598],"iteration":254,"passed_time":0.2906903588,"remaining_time":0.8492718325},
{"learn":[4.597012808],"iteration":255,"passed_time":0.2912046038,"remaining_time":0.8463133798},
{"learn":[4.594161533],"iteration":256,"passed_time":0.2917544295,"remaining_time":0.8434768136},
{"learn":[4.592197259],"iteration":257,"passed_time":0.2922818429,"remaining_time":0.8405935172},
{"learn":[4.58952828],"iteration":258,"passed_time":0.2928121017,"remaining_time":0.8377365535},
{"learn":[4.585816572],"iteration":259,"passed_time":0.2933269936,"remaining_time":0.8348537511},
{"learn":[4.582934052],"iteration":260,"passed_time":0.2938506666,"remaining_time":0.8320139565},
{"learn":[4.582234842],"iteration":261,"passed_time":0.2943514262,"remaining_time":0.8291272998},
{"learn":[4.57571562],"iteration":262,"passed_time":0.2948671556,"remaining_time":0.8263007364},
{"learn":[4.571197349],"iteration":263,"passed_time":0.2954015864,"remaining_time":0.8235438165},
{"learn":[4.56723703],"iteration":264,"passed_time":0.2959323864,"remaining_time":0.8207935999},
{"learn":[4.560335567],"iteration":265,"passed_time":0.2964583339,"remaining_time":0.8180466807},
{"learn":[4.554709345],"iteration":266,"passed_time":0.2969668466,"remaining_time":0.8152685338},
{"learn":[4.552806306],"iteration":267,"passed_time":0.297477388,"remaining_time":0.8125128657},
{"learn":[4.550766241],"iteration":268,"passed_time":0.2979959771,"remaining_time":0.8097957594},
{"learn":[4.549216045],"iteration":269,"passed_time":0.2985111773,"remaining_time":0.8070857756},
{"learn":[4.547687452],"iteration":270,"passed_time":0.2990178774,"remaining_time":0.804369124},
{"learn":[4.545642435],"iteration":271,"passed_time":0.2995151191,"remaining_time":0.801643407},
{"learn":[4.543930359],"iteration":272,"passed_time":0.3000230537,"remaining_time":0.7989624911},
{"learn":[4.541029943],"iteration":273,"passed_time":0.3005903575,"remaining_time":0.7964547428},
{"learn":[4.537781449],"iteration":274,"passed_time":0.3011152858,"remaining_time":0.7938493899},
{"learn":[4.53066128],"iteration":275,"passed_time":0.301650028,"remaining_time":0.7912848562},
{"learn":[4.526763956],"iteration":276,"passed_time":0.3021744248,"remaining_time":0.7887079752},
{"learn":[4.522036004],"iteration":277,"passed_time":0.3027050006,"remaining_time":0.7861619081},
{"learn":[4.515307629],"iteration":278,"passed_time":0.3032457538,"remaining_time":0.7836565896},
{"learn":[4.51109143],"iteration":279,"passed_time":0.3038132245,"remaining_time":0.7812340058},
{"learn":[4.508233494],"iteration":280,"passed_time":0.3043475095,"remaining_time":0.778739713},
{"learn":[4.502555629],"iteration":281,"passed_time":0.304883178,"remaining_time":0.7762628434},
{"learn":[4.500081355],"iteration":282,"passed_time":0.305414151,"remaining_time":0.7737877959},
{"learn":[4.495281743],"iteration":283,"passed_time":0.3059565206,"remaining_time":0.7713551716},
{"learn":[4.492138869],"iteration":284,"passed_time":0.3064871701,"remaining_time":0.7689064091},
{"learn":[4.491708261],"iteration":285,"passed_time":0.3070079897,"remaining_time":0.7664465197},
{"learn":[4.489398865],"iteration":286,"passed_time":0.3075178522,"remaining_time":0.763972922},
{"learn":[4.485796373],"iteration":287,"passed_time":0.3080322125,"remaining_time":0.761524081},
{"learn":[4.479542205],"iteration":288,"passed_time":0.3085622383,"remaining_time":0.7591271677},
{"learn":[4.475986993],"iteration":289,"passed_time":0.3091018146,"remaining_time":0.7567665117},
{"learn":[4.468661855],"iteration":290,"passed_time":0.3096336306,"remaining_time":0.7543994643},
{"learn":[4.463785664],"iteration":291,"passed_time":0.3101697242,"remaining_time":0.7520553588},
{"learn":[4.460445831],"iteration":292,"passed_time":0.3106902653,"remaining_time":0.7496860667},
{"learn":[4.45692492],"iteration":293,"passed_time":0.3112349358,"remaining_time":0.7473872948},
{"learn":[4.454031688],"iteration":294,"passed_time":0.3117858815,"remaining_time":0.7451154118},
{"learn":[4.451672391],"iteration":295,"passed_time":0.3123306846,"remaining_time":0.7428405471},
{"learn":[4.45031553],"iteration":296,"passed_time":0.3128736786,"remaining_time":0.7405730508},
{"learn":[4.446782666],"iteration":297,"passed_time":0.3134017654,"remaining_time":0.7382820111},
{"learn":[4.444369689],"iteration":298,"passed_time":0.3139045233,"remaining_time":0.7359433807},
{"learn":[4.44411683],"iteration":299,"passed_time":0.3144007707,"remaining_time":0.7336017982},
{"learn":[4.440876943],"iteration":300,"passed_time":0.3149553731,"remaining_time":0.7314079928},
{"learn":[4.439336453],"iteration":301,"passed_time":0.3155600525,"remaining_time":0.7293407835},
{"learn":[4.436666901],"iteration":302,"passed_time":0.3161856357,"remaining_time":0.7273313138},
{"learn":[4.433043336],"iteration":303,"passed_time":0.3168049217,"remaining_time":0.7253165313},
{"learn":[4.431419305],"iteration":304,"passed_time":0.3174234424,"remaining_time":0.7233091555},
{"learn":[4.428859646],"iteration":305,"passed_time":0.3181250717,"remaining_time":0.7214993457},
{"learn":[4.424552441],"iteration":306,"passed_time":0.3187699528,"remaining_time":0.7195686557},
{"learn":[4.422706391],"iteration":307,"passed_time":0.3193393682,"remaining_time":0.7174767622},
{"learn":[4.421427994],"iteration":308,"passed_time":0.3198681506,"remaining_time":0.7153038579},
{"learn":[4.418733158],"iteration":309,"passed_time":0.3204071689,"remaining_time":0.7131643436},
{"learn":[4.415656941],"iteration":310,"passed_time":0.3209518562,"remaining_time":0.7110476815},
{"learn":[4.410747417],"iteration":311,"passed_time":0.3214857498,"remaining_time":0.7089172944},
{"learn":[4.408126521],"iteration":312,"passed_time":0.3220240979,"remaining_time":0.7068068859},
{"learn":[4.407843853],"iteration":313,"passed_time":0.3225295835,"remaining_time":0.7046346952},
{"learn":[4.405219398],"iteration":314,"passed_time":0.3230724895,"remaining_time":0.7025544614},
{"learn":[4.402708465],"iteration":315,"passed_time":0.3236033392,"remaining_time":0.7004578608},
{"learn":[4.40104971],"iteration":316,"passed_time":0.3241599752,"remaining_time":0.6984266974},
{"learn":[4.400830038],"iteration":317,"passed_time":0.3246524173,"remaining_time":0.6962671339},
{"learn":[4.39784288],"iteration":318,"passed_time":0.3251787499,"remaining_time":0.6941903721},
{"learn":[4.393741845],"iteration":319,"passed_time":0.3257516563,"remaining_time":0.6922222696},
{"learn":[4.393425936],"iteration":320,"passed_time":0.3262576551,"remaining_time":0.6901213327},
{"learn":[4.390505974],"iteration":321,"passed_time":0.3267836498,"remaining_time":0.6880724055},
{"learn":[4.390305136],"iteration":322,"passed_time":0.327281721,"remaining_time":0.6859743811},
{"learn":[4.38568203],"iteration":323,"passed_time":0.3278079215,"remaining_time":0.6839449226},
{"learn":[4.383057135],"iteration":324,"passed_time":0.3283486995,"remaining_time":0.6819549912},
{"learn":[4.380662684],"iteration":325,"passed_time":0.3288873727,"remaining_time":0.6799695987},
{"learn":[4.37805727],"iteration":326,"passed_time":0.3294144098,"remaining_time":0.6779691065},
{"learn":[4.373708319],"iteration":327,"passed_time":0.3300632999,"remaining_time":0.6762272487},
{"learn":[4.36887921],"iteration":328,"passed_time":0.3306135187,"remaining_time":0.6742907935},
{"learn":[4.367895929],"iteration":329,"passed_time":0.3311516931,"remaining_time":0.672338286},
{"learn":[4.362140573],"iteration":330,"passed_time":0.3317088267,"remaining_time":0.6704326438},
{"learn":[4.361931924],"iteration":331,"passed_time":0.3322296528,"remaining_time":0.6684620724},
{"learn":[4.359656377],"iteration":332,"passed_time":0.3327495949,"remaining_time":0.6664984379},
{"learn":[4.354281355],"iteration":333,"passed_time":0.33328969,"remaining_time":0.6645836333},
{"learn":[4.348589447],"iteration":334,"passed_time":0.3338382747,"remaining_time":0.6626938886},
{"learn":[4.346355698],"iteration":335,"passed_time":0.3343547062,"remaining_time":0.6607485861},
{"learn":[4.343894047],"iteration":336,"passed_time":0.3348946996,"remaining_time":0.6588581182},
{"learn":[4.341561356],"iteration":337,"passed_time":0.3354233828,"remaining_time":0.6569534894},
{"learn":[4.338869061],"iteration":338,"passed_time":0.3359697074,"remaining_time":0.6550913764},
{"learn":[4.333720063],"iteration":339,"passed_time":0.3365155685,"remaining_time":0.6532361035},
{"learn":[4.330892223],"iteration":340,"passed_time":0.3370586346,"remaining_time":0.6513831091},
{"learn":[4.328311474],"iteration":341,"passed_time":0.3376179282,"remaining_time":0.6495689965},
{"learn":[4.324580133],"iteration":342,"passed_time":0.3381767688,"remaining_time":0.6477613326},
{"learn":[4.323354432],"iteration":343,"passed_time":0.3386969407,"remaining_time":0.6458871892},
{"learn":[4.323159553],"iteration":344,"passed_time":0.3392047729,"remaining_time":0.6439974673},
{"learn":[4.318639682],"iteration":345,"passed_time":0.339741274,"remaining_time":0.6421699225},
{"learn":[4.312712208],"iteration":346,"passed_time":0.3402695761,"remaining_time":0.6403343896},
{"learn":[4.311461062],"iteration":347,"passed_time":0.3407901516,"remaining_time":0.6384918931},
{"learn":[4.311178356],"iteration":348,"passed_time":0.3412992763,"remaining_time":0.6366356128},
{"learn":[4.311102505],"iteration":349,"passed_time":0.3418169191,"remaining_time":0.6348028498},
{"learn":[4.310232308],"iteration":350,"passed_time":0.3423270955,"remaining_time":0.6329637748},
{"learn":[4.305128197],"iteration":351,"passed_time":0.3428628424,"remaining_time":0.6311793236},
{"learn":[4.304595496],"iteration":352,"passed_time":0.3433863697,"remaining_time":0.6293795502},
{"learn":[4.3004992],"iteration":353,"passed_time":0.3439355261,"remaining_time":0.6276337566},
{"learn":[4.297581524],"iteration":354,"passed_time":0.3444495445,"remaining_time":0.6258308626},
{"learn":[4.297355825],"iteration":355,"passed_time":0.344981186,"remaining_time":0.6240670892},
{"learn":[4.295758715],"iteration":356,"passed_time":0.3455174742,"remaining_time":0.6223185879},
{"learn":[4.292500657],"iteration":357,"passed_time":0.3460625378,"remaining_time":0.6205925957},
{"learn":[4.290797586],"iteration":358,"passed_time":0.3466010349,"remaining_time":0.6188614578},
{"learn":[4.286410608],"iteration":359,"passed_time":0.3471337203,"remaining_time":0.6171266139},
{"learn":[4.280278245],"iteration":360,"passed_time":0.3476760987,"remaining_time":0.6154155875},
{"learn":[4.279941283],"iteration":361,"passed_time":0.3481836242,"remaining_time":0.6136495919},
{"learn":[4.274426275],"iteration":362,"passed_time":0.3487025664,"remaining_time":0.6119105643},
{"learn":[4.273567658],"iteration":363,"passed_time":0.3492201028,"remaining_time":0.610175784},
{"learn":[4.269488271],"iteration":364,"passed_time":0.3497762212,"remaining_time":0.6085147958},
{"learn":[4.266838205],"iteration":365,"passed_time":0.3502961426,"remaining_time":0.6067971431},
{"learn":[4.263456509],"iteration":366,"passed_time":0.3508434495,"remaining_time":0.6051332522},
{"learn":[4.260360204],"iteration":367,"passed_time":0.3513627488,"remaining_time":0.6034273294},
{"learn":[4.255120549],"iteration":368,"passed_time":0.3519144215,"remaining_time":0.6017831977},
{"learn":[4.252582211],"iteration":369,"passed_time":0.3524818177,"remaining_time":0.6001717436},
{"learn":[4.247857931],"iteration":370,"passed_time":0.3530119428,"remaining_time":0.5985027278},
{"learn":[4.245288911],"iteration":371,"passed_time":0.3535400832,"remaining_time":0.5968364845},
{"learn":[4.24048515],"iteration":372,"passed_time":0.3540892851,"remaining_time":0.5952117474},
{"learn":[4.2378365],"iteration":373,"passed_time":0.3546156114,"remaining_time":0.5935544725},
{"learn":[4.236751063],"iteration":374,"passed_time":0.355152452,"remaining_time":0.5919207533},
{"learn":[4.233240093],"iteration":375,"passed_time":0.355675659,"remaining_time":0.5902702426},
{"learn":[4.230358421],"iteration":376,"passed_time":0.3561954322,"remaining_time":0.5886200379},
{"learn":[4.225853583],"iteration":377,"passed_time":0.3567272366,"remaining_time":0.5869956116},
{"learn":[4.224702126],"iteration":378,"passed_time":0.3572573457,"remaining_time":0.5853741733},
{"learn":[4.224361982],"iteration":379,"passed_time":0.3577510799,"remaining_time":0.5836991304},
{"learn":[4.223787954],"iteration":380,"passed_time":0.3582798788,"remaining_time":0.5820872572},
{"learn":[4.22144054],"iteration":381,"passed_time":0.3588078887,"remaining_time":0.5804797781},
{"learn":[4.217739335],"iteration":382,"passed_time":0.3593610097,"remaining_time":0.578918389},
{"learn":[4.215611665],"iteration":383,"passed_time":0.359897233,"remaining_time":0.5773351446},
{"learn":[4.210236863],"iteration":384,"passed_time":0.3604422374,"remaining_time":0.5757713663},
{"learn":[4.208454294],"iteration":385,"passed_time":0.3609870937,"remaining_time":0.5742126309},
{"learn":[4.207446501],"iteration":386,"passed_time":0.3615018423,"remaining_time":0.5726114453},
{"learn":[4.204985442],"iteration":387,"passed_time":0.3620391024,"remaining_time":0.5710513678},
{"learn":[4.202796622],"iteration":388,"passed_time":0.362586656,"remaining_time":0.5695127167},
{"learn":[4.199774004],"iteration":389,"passed_time":0.3631229882,"remaining_time":0.5679615969},
{"learn":[4.199458358],"iteration":390,"passed_time":0.3636239215,"remaining_time":0.5663605325},
{"learn":[4.19751254],"iteration":391,"passed_time":0.3641592065,"remaining_time":0.5648183611},
{"learn":[4.195201346],"iteration":392,"passed_time":0.3647107171,"remaining_time":0.5633063747},
{"learn":[4.190593508],"iteration":393,"passed_time":0.3652313654,"remaining_time":0.5617517955},
{"learn":[4.187212054],"iteration":394,"passed_time":0.3657649515,"remaining_time":0.5602222675},
{"learn":[4.184984466],"iteration":395,"passed_time":0.3663029754,"remaining_time":0.5587045382},
{"learn":[4.182832144],"iteration":396,"passed_time":0.3668234107,"remaining_time":0.5571650294},
{"learn":[4.179752812],"iteration":397,"passed_time":0.3673474888,"remaining_time":0.5556361515},
{"learn":[4.17878934],"iteration":398,"passed_time":0.3678688153,"remaining_time":0.5541081653},
{"learn":[4.174548229],"iteration":399,"passed_time":0.3684001541,"remaining_time":0.5526002311},
{"learn":[4.168872556],"iteration":400,"passed_time":0.3689299966,"remaining_time":0.5510949325},
{"learn":[4.163926494],"iteration":401,"passed_time":0.3694770185,"remaining_time":0.5496200424},
{"learn":[4.159485076],"iteration":402,"passed_time":0.3700265703,"remaining_time":0.5481535049},
{"learn":[4.155926102],"iteration":403,"passed_time":0.370578745,"remaining_time":0.5466953763},
{"learn":[4.153540115],"iteration":404,"passed_time":0.3711307351,"remaining_time":0.5452414503},
{"learn":[4.150983044],"iteration":405,"passed_time":0.371661427,"remaining_time":0.543760807},
{"learn":[4.146539132],"iteration":406,"passed_time":0.3722177168,"remaining_time":0.5423221279},
{"learn":[4.144869174],"iteration":407,"passed_time":0.3727906676,"remaining_time":0.5409119491},
{"learn":[4.142825962],"iteration":408,"passed_time":0.3733216606,"remaining_time":0.5394452357},
{"learn":[4.142467378],"iteration":409,"passed_time":0.3738191625,"remaining_time":0.5379348924},
{"learn":[4.141800768],"iteration":410,"passed_time":0.3743373537,"remaining_time":0.5364591274},
{"learn":[4.140107084],"iteration":411,"passed_time":0.3748673651,"remaining_time":0.5350048803},
{"learn":[4.136243196],"iteration":412,"passed_time":0.3753931069,"remaining_time":0.5335490406},
{"learn":[4.133618439],"iteration":413,"passed_time":0.375924806,"remaining_time":0.5321061264},
{"learn":[4.131053025],"iteration":414,"passed_time":0.3764654303,"remaining_time":0.5306801848},
{"learn":[4.128379975],"iteration":415,"passed_time":0.3770097846,"remaining_time":0.529263736},
{"learn":[4.127068571],"iteration":416,"passed_time":0.3775417759,"remaining_time":0.5278341855},
{"learn":[4.125969877],"iteration":417,"passed_time":0.3780535895,"remaining_time":0.5263808351},
{"learn":[4.123893633],"iteration":418,"passed_time":0.3785940584,"remaining_time":0.5249717135},
{"learn":[4.119643722],"iteration":419,"passed_time":0.3791462891,"remaining_time":0.5235829707},
{"learn":[4.11465686],"iteration":420,"passed_time":0.379698792,"remaining_time":0.5221985762},
{"learn":[4.111565986],"iteration":421,"passed_time":0.3802317449,"remaining_time":0.5207913472},
{"learn":[4.106322452],"iteration":422,"passed_time":0.3807870211,"remaining_time":0.5194187025},
{"learn":[4.104222175],"iteration":423,"passed_time":0.3813443885,"remaining_time":0.5180527541},
{"learn":[4.103008002],"iteration":424,"passed_time":0.3818602131,"remaining_time":0.516634406},
{"learn":[4.099176337],"iteration":425,"passed_time":0.3823935566,"remaining_time":0.5152439003},
{"learn":[4.096525716],"iteration":426,"passed_time":0.3829440892,"remaining_time":0.5138804757},
{"learn":[4.094967724],"iteration":427,"passed_time":0.383471192,"remaining_time":0.512489537},
{"learn":[4.094683584],"iteration":428,"passed_time":0.3839713896,"remaining_time":0.5110668146},
{"learn":[4.091096563],"iteration":429,"passed_time":0.3844959937,"remaining_time":0.5096807359},
{"learn":[4.089178677],"iteration":430,"passed_time":0.3850478273,"remaining_time":0.5083346026},
{"learn":[4.085335077],"iteration":431,"passed_time":0.3855853172,"remaining_time":0.5069732874},
{"learn":[4.084852122],"iteration":432,"passed_time":0.3861226269,"remaining_time":0.5056155415},
{"learn":[4.080322952],"iteration":433,"passed_time":0.3866583835,"remaining_time":0.5042595509},
{"learn":[4.077449519],"iteration":434,"passed_time":0.3872151673,"remaining_time":0.5029346425},
{"learn":[4.076568374],"iteration":435,"passed_time":0.3877446183,"remaining_time":0.5015779007},
{"learn":[4.076071793],"iteration":436,"passed_time":0.3883136033,"remaining_time":0.5002758779},
{"learn":[4.075027644],"iteration":437,"passed_time":0.3889577462,"remaining_time":0.4990736378},
{"learn":[4.07020837],"iteration":438,"passed_time":0.3896733626,"remaining_time":0.4979652766},
{"learn":[4.06833694],"iteration":439,"passed_time":0.3903166665,"remaining_time":0.4967666664},
{"learn":[4.063936568],"iteration":440,"passed_time":0.3908544886,"remaining_time":0.4954368688},
{"learn":[4.061734926],"iteration":441,"passed_time":0.3913857305,"remaining_time":0.4941023476},
{"learn":[4.060815619],"iteration":442,"passed_time":0.3919182094,"remaining_time":0.4927730082},
{"learn":[4.056407489],"iteration":443,"passed_time":0.3924705058,"remaining_time":0.4914720748},
{"learn":[4.05238936],"iteration":444,"passed_time":0.3929969136,"remaining_time":0.4901422181},
{"learn":[4.049685254],"iteration":445,"passed_time":0.3935250348,"remaining_time":0.4888180926},
{"learn":[4.045162016],"iteration":446,"passed_time":0.3940797802,"remaining_time":0.4875304664},
{"learn":[4.042955482],"iteration":447,"passed_time":0.394643213,"remaining_time":0.486256816},
{"learn":[4.041467663],"iteration":448,"passed_time":0.3951548609,"remaining_time":0.4849227803},
{"learn":[4.038920476],"iteration":449,"passed_time":0.3956976812,"remaining_time":0.4836304993},
{"learn":[4.036694383],"iteration":450,"passed_time":0.3962450522,"remaining_time":0.4823470813},
{"learn":[4.034999007],"iteration":451,"passed_time":0.3967871552,"remaining_time":0.4810605333},
{"learn":[4.031928018],"iteration":452,"passed_time":0.3973153741,"remaining_time":0.4797605069},
{"learn":[4.028718143],"iteration":453,"passed_time":0.3978486736,"remaining_time":0.4784699907},
{"learn":[4.027401978],"iteration":454,"passed_time":0.3983760654,"remaining_time":0.4771757267},
{"learn":[4.025930598],"iteration":455,"passed_time":0.3988917219,"remaining_time":0.4758708261},
{"learn":[4.021074523],"iteration":456,"passed_time":0.3994291149,"remaining_time":0.4745952066},
{"learn":[4.020268486],"iteration":457,"passed_time":0.3999529977,"remaining_time":0.4733068226},
{"learn":[4.017986361],"iteration":458,"passed_time":0.4004795617,"remaining_time":0.47202493},
{"learn":[4.014814804],"iteration":459,"passed_time":0.4011474522,"remaining_time":0.4709122265},
{"learn":[4.009704796],"iteration":460,"passed_time":0.4017920307,"remaining_time":0.4697741964},
{"learn":[4.008440457],"iteration":461,"passed_time":0.4023183809,"remaining_time":0.4685006254},
{"learn":[4.004854849],"iteration":462,"passed_time":0.4028510751,"remaining_time":0.4672376401},
{"learn":[4.000898028],"iteration":463,"passed_time":0.403387236,"remaining_time":0.4659818071},
{"learn":[3.996617985],"iteration":464,"passed_time":0.4039345141,"remaining_time":0.4647418604},
{"learn":[3.995443319],"iteration":465,"passed_time":0.4044707679,"remaining_time":0.4634922533},
{"learn":[3.990771995],"iteration":466,"passed_time":0.4050065477,"remaining_time":0.4622451604},
{"learn":[3.989249359],"iteration":467,"passed_time":0.4055331261,"remaining_time":0.4609906476},
{"learn":[3.986599538],"iteration":468,"passed_time":0.4060568415,"remaining_time":0.4597359975},
{"learn":[3.985628919],"iteration":469,"passed_time":0.4065906734,"remaining_time":0.4584958658},
{"learn":[3.985086112],"iteration":470,"passed_time":0.407105856,"remaining_time":0.4572377873},
{"learn":[3.98466839],"iteration":471,"passed_time":0.4076410697,"remaining_time":0.4560052645},
{"learn":[3.984233894],"iteration":472,"passed_time":0.4081678787,"remaining_time":0.4547663258},
{"learn":[3.981855845],"iteration":473,"passed_time":0.408707692,"remaining_time":0.4535448227},
{"learn":[3.978684264],"iteration":474,"passed_time":0.4092485741,"remaining_time":0.4523273713},
{"learn":[3.974361269],"iteration":475,"passed_time":0.4097840272,"remaining_time":0.4511067862},
{"learn":[3.972074049],"iteration":476,"passed_time":0.4103235418,"remaining_time":0.449893527},
{"learn":[3.97191982],"iteration":477,"passed_time":0.4108493893,"remaining_time":0.4486681615},
{"learn":[3.969616848],"iteration":478,"passed_time":0.4113871298,"remaining_time":0.4474586526},
{"learn":[3.968533527],"iteration":479,"passed_time":0.4118912735,"remaining_time":0.4462155463},
{"learn":[3.967568753],"iteration":480,"passed_time":0.4123927537,"remaining_time":0.4449726386},
{"learn":[3.966232553],"iteration":481,"passed_time":0.4129347286,"remaining_time":0.4437763265},
{"learn":[3.961522393],"iteration":482,"passed_time":0.4134802269,"remaining_time":0.4425864955},
{"learn":[3.955829553],"iteration":483,"passed_time":0.4140117411,"remaining_time":0.4413844182},
{"learn":[3.954248095],"iteration":484,"passed_time":0.4145115239,"remaining_time":0.440151412},
{"learn":[3.951922606],"iteration":485,"passed_time":0.4150689274,"remaining_time":0.4389823635},
{"learn":[3.94978202],"iteration":486,"passed_time":0.4156024038,"remaining_time":0.4377906225},
{"learn":[3.949518999],"iteration":487,"passed_time":0.4161307027,"remaining_time":0.4365961471},
{"learn":[3.945431216],"iteration":488,"passed_time":0.4166694648,"remaining_time":0.4354153303},
{"learn":[3.943249086],"iteration":489,"passed_time":0.4172261669,"remaining_time":0.4342558063},
{"learn":[3.941981548],"iteration":490,"passed_time":0.4177526196,"remaining_time":0.4330673795},
{"learn":[3.936600517],"iteration":491,"passed_time":0.4182722911,"remaining_time":0.431874642},
{"learn":[3.934476885],"iteration":492,"passed_time":0.4188098675,"remaining_time":0.4307030483},
{"learn":[3.93045798],"iteration":493,"passed_time":0.4193557902,"remaining_time":0.4295425705},
{"learn":[3.925977375],"iteration":494,"passed_time":0.4198875509,"remaining_time":0.4283701277},
{"learn":[3.92457993],"iteration":495,"passed_time":0.4204066989,"remaining_time":0.4271874521},
{"learn":[3.919849146],"iteration":496,"passed_time":0.420950291,"remaining_time":0.4260321859},
{"learn":[3.919681964],"iteration":497,"passed_time":0.4214908712,"remaining_time":0.4248763401},
{"learn":[3.917633027],"iteration":498,"passed_time":0.422026563,"remaining_time":0.4237180522},
{"learn":[3.916616419],"iteration":499,"passed_time":0.422552436,"remaining_time":0.422552436},
{"learn":[3.912896166],"iteration":500,"passed_time":0.4230892542,"remaining_time":0.4214002752},
{"learn":[3.912769674],"iteration":501,"passed_time":0.4235749135,"remaining_time":0.4201998146},
{"learn":[3.909373788],"iteration":502,"passed_time":0.4241091273,"remaining_time":0.4190501715},
{"learn":[3.906706036],"iteration":503,"passed_time":0.4246403573,"remaining_time":0.4179000341},
{"learn":[3.903895664],"iteration":504,"passed_time":0.4251855106,"remaining_time":0.4167659955},
{"learn":[3.902982967],"iteration":505,"passed_time":0.4257143411,"remaining_time":0.4156183488},
{"learn":[3.900905528],"iteration":506,"passed_time":0.4262552488,"remaining_time":0.4144848869},
{"learn":[3.897463465],"iteration":507,"passed_time":0.4267913953,"remaining_time":0.4133491466},
{"learn":[3.895918033],"iteration":508,"passed_time":0.4273258348,"remaining_time":0.4122141157},
{"learn":[3.893921936],"iteration":509,"passed_time":0.427866592,"remaining_time":0.41108751},
{"learn":[3.890237934],"iteration":510,"passed_time":0.4284070578,"remaining_time":0.4099629183},
{"learn":[3.887311613],"iteration":511,"passed_time":0.4289427967,"remaining_time":0.4088361031},
{"learn":[3.884869735],"iteration":512,"passed_time":0.429572351,"remaining_time":0.4078006529},
{"learn":[3.882101231],"iteration":513,"passed_time":0.4301189149,"remaining_time":0.4066883126},
{"learn":[3.88060368],"iteration":514,"passed_time":0.4306947876,"remaining_time":0.4056057708},
{"learn":[3.877726076],"iteration":515,"passed_time":0.4312305153,"remaining_time":0.4044875376},
{"learn":[3.874938145],"iteration":516,"passed_time":0.4317758416,"remaining_time":0.4033805251},
{"learn":[3.874340833],"iteration":517,"passed_time":0.4323072276,"remaining_time":0.4022627099},
{"learn":[3.873105224],"iteration":518,"passed_time":0.4328687005,"remaining_time":0.4011750385},
{"learn":[3.869800236],"iteration":519,"passed_time":0.4334172612,"remaining_time":0.4000774719},
{"learn":[3.867932518],"iteration":520,"passed_time":0.4339741987,"remaining_time":0.3989897144},
{"learn":[3.866666962],"iteration":521,"passed_time":0.4345140456,"remaining_time":0.3978883406},
{"learn":[3.865527652],"iteration":522,"passed_time":0.4350618321,"remaining_time":0.3967963555},
{"learn":[3.861900081],"iteration":523,"passed_time":0.4356025212,"remaining_time":0.3957000002},
{"learn":[3.858502887],"iteration":524,"passed_time":0.4361479195,"remaining_time":0.3946100224},
{"learn":[3.858335097],"iteration":525,"passed_time":0.4366597603,"remaining_time":0.3934918753},
{"learn":[3.855719306],"iteration":526,"passed_time":0.4372270361,"remaining_time":0.3924257838},
{"learn":[3.855137428],"iteration":527,"passed_time":0.4377760219,"remaining_time":0.3913452317},
{"learn":[3.851985706],"iteration":528,"passed_time":0.4383125038,"remaining_time":0.3902555563},
{"learn":[3.851051809],"iteration":529,"passed_time":0.4388313347,"remaining_time":0.3891523157},
{"learn":[3.850679146],"iteration":530,"passed_time":0.4393612781,"remaining_time":0.3880610912},
{"learn":[3.848179484],"iteration":531,"passed_time":0.4399007919,"remaining_time":0.3869803959},
{"learn":[3.844551071],"iteration":532,"passed_time":0.4404487522,"remaining_time":0.3859091318},
{"learn":[3.841604794],"iteration":533,"passed_time":0.4409909656,"remaining_time":0.3848348127},
{"learn":[3.83969656],"iteration":534,"passed_time":0.441534304,"remaining_time":0.3837634605},
{"learn":[3.836811463],"iteration":535,"passed_time":0.4420938386,"remaining_time":0.3827080991},
{"learn":[3.834182551],"iteration":536,"passed_time":0.4426443168,"remaining_time":0.3816467759},
{"learn":[3.828012842],"iteration":537,"passed_time":0.4432059458,"remaining_time":0.3805969274},
{"learn":[3.826636176],"iteration":538,"passed_time":0.4437361261,"remaining_time":0.3795219929},
{"learn":[3.826189798],"iteration":539,"passed_time":0.4443320668,"remaining_time":0.378505094},
{"learn":[3.824104738],"iteration":540,"passed_time":0.4448979343,"remaining_time":0.3774642363},
{"learn":[3.82300218],"iteration":541,"passed_time":0.4454155082,"remaining_time":0.3763843225},
{"learn":[3.817146402],"iteration":542,"passed_time":0.4459461177,"remaining_time":0.3753174508},
{"learn":[3.814638044],"iteration":543,"passed_time":0.4464848189,"remaining_time":0.3742593335},
{"learn":[3.812979573],"iteration":544,"passed_time":0.4470074455,"remaining_time":0.3731897022},
{"learn":[3.811938825],"iteration":545,"passed_time":0.447549185,"remaining_time":0.3721379671},
{"learn":[3.811479418],"iteration":546,"passed_time":0.4480484443,"remaining_time":0.3710529164},
{"learn":[3.80742981],"iteration":547,"passed_time":0.4485729203,"remaining_time":0.3699908029},
{"learn":[3.805097043],"iteration":548,"passed_time":0.4491036098,"remaining_time":0.3689357523},
{"learn":[3.801577232],"iteration":549,"passed_time":0.4496378909,"remaining_time":0.3678855471},
{"learn":[3.799762083],"iteration":550,"passed_time":0.4501745457,"remaining_time":0.3668391489},
{"learn":[3.796393455],"iteration":551,"passed_time":0.4506978417,"remaining_time":0.3657837555},
{"learn":[3.793486459],"iteration":552,"passed_time":0.4512064048,"remaining_time":0.3647183778},
{"learn":[3.792006091],"iteration":553,"passed_time":0.4517462108,"remaining_time":0.3636801625},
{"learn":[3.78932128],"iteration":554,"passed_time":0.4522779692,"remaining_time":0.3626372906},
{"learn":[3.787581812],"iteration":555,"passed_time":0.4528011338,"remaining_time":0.3615893946},
{"learn":[3.785308865],"iteration":556,"passed_time":0.4533523405,"remaining_time":0.3605656855},
{"learn":[3.78465475],"iteration":557,"passed_time":0.4538469314,"remaining_time":0.3594988238},
{"learn":[3.780498869],"iteration":558,"passed_time":0.4544416552,"remaining_time":0.3585130052},
{"learn":[3.778734909],"iteration":559,"passed_time":0.4549808223,"remaining_time":0.3574849318},
{"learn":[3.778652349],"iteration":560,"passed_time":0.455510716,"remaining_time":0.3564513446},
{"learn":[3.777928006],"iteration":561,"passed_time":0.4560508832,"remaining_time":0.3554275566},
{"learn":[3.776131406],"iteration":562,"passed_time":0.4565962999,"remaining_time":0.3544095614},
{"learn":[3.772925617],"iteration":563,"passed_time":0.4571559946,"remaining_time":0.3534042795},
{"learn":[3.7727745],"iteration":564,"passed_time":0.4576858003,"remaining_time":0.3523775631},
{"learn":[3.771763073],"iteration":565,"passed_time":0.458213851,"remaining_time":0.3513512568},
{"learn":[3.768738162],"iteration":566,"passed_time":0.4587306444,"remaining_time":0.3503181111},
{"learn":[3.767220794],"iteration":567,"passed_time":0.4592447429,"remaining_time":0.349284734},
{"learn":[3.766691102],"iteration":568,"passed_time":0.4597816892,"remaining_time":0.3482704887},
{"learn":[3.766259335],"iteration":569,"passed_time":0.4603056088,"remaining_time":0.3472480908},
{"learn":[3.76116362],"iteration":570,"passed_time":0.4608375368,"remaining_time":0.3462334559},
{"learn":[3.758633056],"iteration":571,"passed_time":0.4613745143,"remaining_time":0.345224287},
{"learn":[3.754603809],"iteration":572,"passed_time":0.4619245466,"remaining_time":0.3442264946},
{"learn":[3.754070549],"iteration":573,"passed_time":0.4624575338,"remaining_time":0.3432176122},
{"learn":[3.750534319],"iteration":574,"passed_time":0.4630110799,"remaining_time":0.3422255808},
{"learn":[3.746491516],"iteration":575,"passed_time":0.463556146,"remaining_time":0.3412288297},
{"learn":[3.744210544],"iteration":576,"passed_time":0.4640914862,"remaining_time":0.3402265142},
{"learn":[3.742929991],"iteration":577,"passed_time":0.4646278969,"remaining_time":0.339226596},
{"learn":[3.740402992],"iteration":578,"passed_time":0.4651788058,"remaining_time":0.3382388208},
{"learn":[3.739644243],"iteration":579,"passed_time":0.4656891703,"remaining_time":0.3372231923},
{"learn":[3.737529404],"iteration":580,"passed_time":0.4662003626,"remaining_time":0.3362099},
{"learn":[3.737196923],"iteration":581,"passed_time":0.4667116246,"remaining_time":0.3351983833},
{"learn":[3.733954464],"iteration":582,"passed_time":0.4672440138,"remaining_time":0.3342036942},
{"learn":[3.731608623],"iteration":583,"passed_time":0.467767128,"remaining_time":0.3332039816},
{"learn":[3.729843952],"iteration":584,"passed_time":0.4683045074,"remaining_time":0.332216018},
{"learn":[3.727223798],"iteration":585,"passed_time":0.4688281163,"remaining_time":0.3312198637},
{"learn":[3.725351667],"iteration":586,"passed_time":0.4693767234,"remaining_time":0.3302429076},
{"learn":[3.725026912],"iteration":587,"passed_time":0.4699089742,"remaining_time":0.3292559479},
{"learn":[3.721974565],"iteration":588,"passed_time":0.4704491669,"remaining_time":0.328276074},
{"learn":[3.720269493],"iteration":589,"passed_time":0.470992928,"remaining_time":0.3273001703},
{"learn":[3.718907466],"iteration":590,"passed_time":0.4715395648,"remaining_time":0.3263277191},
{"learn":[3.715602912],"iteration":591,"passed_time":0.4720723423,"remaining_time":0.3253471548},
{"learn":[3.714463059],"iteration":592,"passed_time":0.4726113277,"remaining_time":0.3243723615},
{"learn":[3.710802077],"iteration":593,"passed_time":0.4731924123,"remaining_time":0.3234278105},
{"learn":[3.708032435],"iteration":594,"passed_time":0.4737401628,"remaining_time":0.3224617915},
{"learn":[3.703788939],"iteration":595,"passed_time":0.4742826349,"remaining_time":0.3214935982},
{"learn":[3.702500944],"iteration":596,"passed_time":0.4748191088,"remaining_time":0.320522782},
{"learn":[3.698196925],"iteration":597,"passed_time":0.4753626361,"remaining_time":0.3195581601},
{"learn":[3.69658891],"iteration":598,"passed_time":0.4758848224,"remaining_time":0.3185806574},
{"learn":[3.696124066],"iteration":599,"passed_time":0.476397013,"remaining_time":0.3175980087},
{"learn":[3.693537052],"iteration":600,"passed_time":0.476950098,"remaining_time":0.316644075},
{"learn":[3.691343275],"iteration":601,"passed_time":0.4774771471,"remaining_time":0.3156742601},
{"learn":[3.690973831],"iteration":602,"passed_time":0.4780060569,"remaining_time":0.3147071386},
{"learn":[3.686151073],"iteration":603,"passed_time":0.4785628151,"remaining_time":0.3137597264},
{"learn":[3.683921982],"iteration":604,"passed_time":0.4791153484,"remaining_time":0.3128108473},
{"learn":[3.679975271],"iteration":605,"passed_time":0.4796346997,"remaining_time":0.3118417024},
{"learn":[3.674047638],"iteration":606,"passed_time":0.4801795796,"remaining_time":0.310890568},
{"learn":[3.673151794],"iteration":607,"passed_time":0.4807329159,"remaining_time":0.3099462221},
{"learn":[3.670953108],"iteration":608,"passed_time":0.4812764904,"remaining_time":0.3089968929},
{"learn":[3.6703947],"iteration":609,"passed_time":0.4818007415,"remaining_time":0.3080365396},
{"learn":[3.668433805],"iteration":610,"passed_time":0.4823646646,"remaining_time":0.3071028716},
{"learn":[3.668304956],"iteration":611,"passed_time":0.482885136,"remaining_time":0.306142864},
{"learn":[3.667880012],"iteration":612,"passed_time":0.4834003618,"remaining_time":0.3051809788},
{"learn":[3.667282264],"iteration":613,"passed_time":0.4839283284,"remaining_time":0.3042285583},
{"learn":[3.664611483],"iteration":614,"passed_time":0.4844567915,"remaining_time":0.3032778288},
{"learn":[3.662543394],"iteration":615,"passed_time":0.4849857389,"remaining_time":0.3023287723},
{"learn":[3.659041959],"iteration":616,"passed_time":0.4855352875,"remaining_time":0.3013938657},
{"learn":[3.656868545],"iteration":617,"passed_time":0.4860786387,"remaining_time":0.3004563754},
{"learn":[3.654785614],"iteration":618,"passed_time":0.4866809034,"remaining_time":0.2995564203},
{"learn":[3.654566096],"iteration":619,"passed_time":0.4872004324,"remaining_time":0.2986067166},
{"learn":[3.651007045],"iteration":620,"passed_time":0.4877569023,"remaining_time":0.2976809436},
{"learn":[3.648921786],"iteration":621,"passed_time":0.4883032934,"remaining_time":0.296750233},
{"learn":[3.647655706],"iteration":622,"passed_time":0.4888416696,"remaining_time":0.295815906},
{"learn":[3.647241144],"iteration":623,"passed_time":0.4893696506,"remaining_time":0.2948765843},
{"learn":[3.644195689],"iteration":624,"passed_time":0.4899070621,"remaining_time":0.2939442372},
{"learn":[3.642632246],"iteration":625,"passed_time":0.490445403,"remaining_time":0.2930137072},
{"learn":[3.642523322],"iteration":626,"passed_time":0.4908387354,"remaining_time":0.2919981632},
{"learn":[3.641494659],"iteration":627,"passed_time":0.491358467,"remaining_time":0.2910594741},
{"learn":[3.63976496],"iteration":628,"passed_time":0.4918897466,"remaining_time":0.2901289284},
{"learn":[3.637945652],"iteration":629,"passed_time":0.4924297456,"remaining_time":0.2892047712},
{"learn":[3.636233667],"iteration":630,"passed_time":0.4929672507,"remaining_time":0.2882803732},
{"learn":[3.635304404],"iteration":631,"passed_time":0.4935072705,"remaining_time":0.2873586638},
{"learn":[3.632234951],"iteration":632,"passed_time":0.4940397053,"remaining_time":0.2864337628},
{"learn":[3.631630987],"iteration":633,"passed_time":0.4945618219,"remaining_time":0.2855041433},
{"learn":[3.630301009],"iteration":634,"passed_time":0.4950898414,"remaining_time":0.2845792002},
{"learn":[3.629077964],"iteration":635,"passed_time":0.4956352229,"remaining_time":0.283665442},
{"learn":[3.628004522],"iteration":636,"passed_time":0.4961749041,"remaining_time":0.2827495921},
{"learn":[3.625062876],"iteration":637,"passed_time":0.4966949359,"remaining_time":0.2818237724},
{"learn":[3.624917986],"iteration":638,"passed_time":0.4972078695,"remaining_time":0.2808952127},
{"learn":[3.622887087],"iteration":639,"passed_time":0.4977386039,"remaining_time":0.2799779647},
{"learn":[3.621220865],"iteration":640,"passed_time":0.4982832072,"remaining_time":0.2790696901},
{"learn":[3.621143844],"iteration":641,"passed_time":0.4988000558,"remaining_time":0.2781470716},
{"learn":[3.620822821],"iteration":642,"passed_time":0.4993071122,"remaining_time":0.2772202785},
{"learn":[3.619202826],"iteration":643,"passed_time":0.4998534232,"remaining_time":0.2763164886},
{"learn":[3.618204882],"iteration":644,"passed_time":0.500377587,"remaining_time":0.2754016176},
{"learn":[3.614259666],"iteration":645,"passed_time":0.5009251537,"remaining_time":0.2745007808},
{"learn":[3.613415661],"iteration":646,"passed_time":0.501467111,"remaining_time":0.2735979755},
{"learn":[3.611096773],"iteration":647,"passed_time":0.501997895,"remaining_time":0.2726902146},
{"learn":[3.610820695],"iteration":648,"passed_time":0.5025249353,"remaining_time":0.2717815906},
{"learn":[3.609290065],"iteration":649,"passed_time":0.5030706803,"remaining_time":0.2708842125},
{"learn":[3.60897947],"iteration":650,"passed_time":0.5035840755,"remaining_time":0.269970572},
{"learn":[3.606570702],"iteration":651,"passed_time":0.5041257782,"remaining_time":0.2690732681},
{"learn":[3.606292637],"iteration":652,"passed_time":0.504654736,"remaining_time":0.2681702808},
{"learn":[3.602753838],"iteration":653,"passed_time":0.5051863462,"remaining_time":0.2672698407},
{"learn":[3.599755869],"iteration":654,"passed_time":0.505721801,"remaining_time":0.2663725517},
{"learn":[3.599509575],"iteration":655,"passed_time":0.5062481448,"remaining_time":0.2654715881},
{"learn":[3.595337722],"iteration":656,"passed_time":0.5067991289,"remaining_time":0.264584629},
{"learn":[3.595168561],"iteration":657,"passed_time":0.5073023112,"remaining_time":0.2636738456},
{"learn":[3.59290559],"iteration":658,"passed_time":0.5078292779,"remaining_time":0.2627766066},
{"learn":[3.592015928],"iteration":659,"passed_time":0.5083707148,"remaining_time":0.261887944},
{"learn":[3.590680403],"iteration":660,"passed_time":0.5088815068,"remaining_time":0.2609846154},
{"learn":[3.590361532],"iteration":661,"passed_time":0.5094097969,"remaining_time":0.2600914069},
{"learn":[3.589069739],"iteration":662,"passed_time":0.5099391246,"remaining_time":0.2591998265},
{"learn":[3.585010186],"iteration":663,"passed_time":0.5104722631,"remaining_time":0.2583112657},
{"learn":[3.582997552],"iteration":664,"passed_time":0.5110202538,"remaining_time":0.2574312557},
{"learn":[3.582119256],"iteration":665,"passed_time":0.5115587317,"remaining_time":0.256547472},
{"learn":[3.579019356],"iteration":666,"passed_time":0.5121140399,"remaining_time":0.2556731264},
{"learn":[3.57719559],"iteration":667,"passed_time":0.512695233,"remaining_time":0.2548126008},
{"learn":[3.574050046],"iteration":668,"passed_time":0.5132430147,"remaining_time":0.2539363795},
{"learn":[3.572204518],"iteration":669,"passed_time":0.513776315,"remaining_time":0.2530540059},
{"learn":[3.569508025],"iteration":670,"passed_time":0.5143225003,"remaining_time":0.2521789905},
{"learn":[3.566268704],"iteration":671,"passed_time":0.5148510658,"remaining_time":0.2512963535},
{"learn":[3.562564052],"iteration":672,"passed_time":0.5154433593,"remaining_time":0.2504457333},
{"learn":[3.561173586],"iteration":673,"passed_time":0.5159725965,"remaining_time":0.2495653805},
{"learn":[3.559551904],"iteration":674,"passed_time":0.5164995152,"remaining_time":0.2486849518},
{"learn":[3.558593054],"iteration":675,"passed_time":0.5170305314,"remaining_time":0.2478075328},
{"learn":[3.555647008],"iteration":676,"passed_time":0.5175570642,"remaining_time":0.2469289981},
{"learn":[3.553100059],"iteration":677,"passed_time":0.5180934932,"remaining_time":0.2460562018},
{"learn":[3.55085578],"iteration":678,"passed_time":0.51864739,"remaining_time":0.2451926542},
{"learn":[3.550737965],"iteration":679,"passed_time":0.5191708853,"remaining_time":0.2443157107},
{"learn":[3.549408772],"iteration":680,"passed_time":0.5197276178,"remaining_time":0.2434553745},
{"learn":[3.547390589],"iteration":681,"passed_time":0.5202571616,"remaining_time":0.2425832513},
{"learn":[3.54723575],"iteration":682,"passed_time":0.5207582407,"remaining_time":0.2416989199},
{"learn":[3.543988891],"iteration":683,"passed_time":0.5213163014,"remaining_time":0.240842034},
{"learn":[3.543868508],"iteration":684,"passed_time":0.5218429006,"remaining_time":0.2399715528},
{"learn":[3.542752124],"iteration":685,"passed_time":0.5223746109,"remaining_time":0.2391044137},
{"learn":[3.541334315],"iteration":686,"passed_time":0.5228978444,"remaining_time":0.2382343891},
{"learn":[3.540208266],"iteration":687,"passed_time":0.5234300358,"remaining_time":0.2373694349},
{"learn":[3.537730983],"iteration":688,"passed_time":0.5239912349,"remaining_time":0.23651854},
{"learn":[3.53419867],"iteration":689,"passed_time":0.5245522011,"remaining_time":0.2356683802},
{"learn":[3.532628335],"iteration":690,"passed_time":0.525092606,"remaining_time":0.2348098629},
{"learn":[3.532204987],"iteration":691,"passed_time":0.525627373,"remaining_time":0.2339497556},
{"learn":[3.530618147],"iteration":692,"passed_time":0.5261633537,"remaining_time":0.233091125},
{"learn":[3.528909306],"iteration":693,"passed_time":0.526721573,"remaining_time":0.2322432296},
{"learn":[3.526700678],"iteration":694,"passed_time":0.5272756587,"remaining_time":0.2313943538},
{"learn":[3.526439574],"iteration":695,"passed_time":0.5277978145,"remaining_time":0.2305323788},
{"learn":[3.525784216],"iteration":696,"passed_time":0.5283220631,"remaining_time":0.2296722886},
{"learn":[3.524112693],"iteration":697,"passed_time":0.528856349,"remaining_time":0.2288175034},
{"learn":[3.522813541],"iteration":698,"passed_time":0.5293897718,"remaining_time":0.2279632637},
{"learn":[3.519148203],"iteration":699,"passed_time":0.5299512311,"remaining_time":0.2271219562},
{"learn":[3.517236747],"iteration":700,"passed_time":0.5305154797,"remaining_time":0.2262826369},
{"learn":[3.515603888],"iteration":701,"passed_time":0.5310666816,"remaining_time":0.2254385629},
{"learn":[3.51263524],"iteration":702,"passed_time":0.5316038016,"remaining_time":0.2245893728},
{"learn":[3.51123442],"iteration":703,"passed_time":0.5321384838,"remaining_time":0.2237400443},
{"learn":[3.50828027],"iteration":704,"passed_time":0.5326819046,"remaining_time":0.222895265},
{"learn":[3.508265537],"iteration":705,"passed_time":0.5330181424,"remaining_time":0.2219650621},
{"learn":[3.506774876],"iteration":706,"passed_time":0.5335493011,"remaining_time":0.22111732},
{"learn":[3.50552068],"iteration":707,"passed_time":0.5340858511,"remaining_time":0.2202726956},
{"learn":[3.501973993],"iteration":708,"passed_time":0.5346183067,"remaining_time":0.2194272599},
{"learn":[3.498880354],"iteration":709,"passed_time":0.5351471349,"remaining_time":0.2185812241},
{"learn":[3.497370959],"iteration":710,"passed_time":0.5356672347,"remaining_time":0.2177325328},
{"learn":[3.496050455],"iteration":711,"passed_time":0.5362096404,"remaining_time":0.2168937871},
{"learn":[3.495630067],"iteration":712,"passed_time":0.5367310653,"remaining_time":0.2160474274},
{"learn":[3.49550669],"iteration":713,"passed_time":0.5373039012,"remaining_time":0.2152225711},
{"learn":[3.493652375],"iteration":714,"passed_time":0.5378791846,"remaining_time":0.2143993953},
{"learn":[3.491915684],"iteration":715,"passed_time":0.5384232539,"remaining_time":0.2135645309},
{"learn":[3.490303956],"iteration":716,"passed_time":0.5389670686,"remaining_time":0.2127303771},
{"learn":[3.488363853],"iteration":717,"passed_time":0.539507371,"remaining_time":0.2118956527},
{"learn":[3.485483936],"iteration":718,"passed_time":0.5400348053,"remaining_time":0.2110567181},
{"learn":[3.483763466],"iteration":719,"passed_time":0.5405759675,"remaining_time":0.2102239874},
{"learn":[3.481642352],"iteration":720,"passed_time":0.5411479532,"remaining_time":0.209403993},
{"learn":[3.479826119],"iteration":721,"passed_time":0.5417004393,"remaining_time":0.2085771775},
{"learn":[3.478588728],"iteration":722,"passed_time":0.5422478792,"remaining_time":0.2077491875},
{"learn":[3.475390887],"iteration":723,"passed_time":0.542804811,"remaining_time":0.2069255909},
{"learn":[3.472636852],"iteration":724,"passed_time":0.5433564485,"remaining_time":0.2061007218},
{"learn":[3.47061883],"iteration":725,"passed_time":0.5439384154,"remaining_time":0.2052880521},
{"learn":[3.46953149],"iteration":726,"passed_time":0.5444699231,"remaining_time":0.2044570688},
{"learn":[3.467217162],"iteration":727,"passed_time":0.5450242714,"remaining_time":0.2036354421},
{"learn":[3.465686216],"iteration":728,"passed_time":0.5455661454,"remaining_time":0.2028099114},
{"learn":[3.462631216],"iteration":729,"passed_time":0.5461072861,"remaining_time":0.2019848866},
{"learn":[3.461451053],"iteration":730,"passed_time":0.5466339574,"remaining_time":0.201155314},
{"learn":[3.458950469],"iteration":731,"passed_time":0.5471959571,"remaining_time":0.2003395034},
{"learn":[3.458072145],"iteration":732,"passed_time":0.5477383075,"remaining_time":0.199517228},
{"learn":[3.454364268],"iteration":733,"passed_time":0.5482849003,"remaining_time":0.1986972527},
{"learn":[3.453243406],"iteration":734,"passed_time":0.5488069616,"remaining_time":0.1978691766},
{"learn":[3.453017963],"iteration":735,"passed_time":0.5493283297,"remaining_time":0.1970416835},
{"learn":[3.45201581],"iteration":736,"passed_time":0.549857193,"remaining_time":0.1962176957},
{"learn":[3.449510107],"iteration":737,"passed_time":0.5504123451,"remaining_time":0.1954038407},
{"learn":[3.447189189],"iteration":738,"passed_time":0.5509389996,"remaining_time":0.194580621},
{"learn":[3.446423605],"iteration":739,"passed_time":0.5515978417,"remaining_time":0.1938046471},
{"learn":[3.445531987],"iteration":740,"passed_time":0.5521744301,"remaining_time":0.1930002394},
{"learn":[3.445328199],"iteration":741,"passed_time":0.5527242757,"remaining_time":0.1921871471},
{"learn":[3.443327544],"iteration":742,"passed_time":0.5532687301,"remaining_time":0.1913728986},
{"learn":[3.441475798],"iteration":743,"passed_time":0.5538171467,"remaining_time":0.1905607387},
{"learn":[3.439046501],"iteration":744,"passed_time":0.5543596604,"remaining_time":0.1897472663},
{"learn":[3.435899469],"iteration":745,"passed_time":0.5549040812,"remaining_time":0.1889351697},
{"learn":[3.433988352],"iteration":746,"passed_time":0.5554566329,"remaining_time":0.1881265437},
{"learn":[3.433413263],"iteration":747,"passed_time":0.556009087,"remaining_time":0.1873185694},
{"learn":[3.429944699],"iteration":748,"passed_time":0.5565622864,"remaining_time":0.1865115272},
{"learn":[3.429291634],"iteration":749,"passed_time":0.5571110232,"remaining_time":0.1857036744},
{"learn":[3.429175603],"iteration":750,"passed_time":0.5576395039,"remaining_time":0.1848897956},
{"learn":[3.428780323],"iteration":751,"passed_time":0.5581370939,"remaining_time":0.1840664884},
{"learn":[3.423893341],"iteration":752,"passed_time":0.5587740905,"remaining_time":0.1832897747},
{"learn":[3.421024316],"iteration":753,"passed_time":0.5593801301,"remaining_time":0.1825033316},
{"learn":[3.420969872],"iteration":754,"passed_time":0.5599460136,"remaining_time":0.1817043355},
{"learn":[3.419544785],"iteration":755,"passed_time":0.5736599903,"remaining_time":0.1851495207},
{"learn":[3.417057977],"iteration":756,"passed_time":0.5743905877,"remaining_time":0.184381655},
{"learn":[3.415160245],"iteration":757,"passed_time":0.5750339332,"remaining_time":0.1835860314},
{"learn":[3.412854597],"iteration":758,"passed_time":0.5757199751,"remaining_time":0.1828043663},
{"learn":[3.410926347],"iteration":759,"passed_time":0.5763055863,"remaining_time":0.1819912378},
{"learn":[3.408963843],"iteration":760,"passed_time":0.5769314666,"remaining_time":0.1811913542},
{"learn":[3.407629634],"iteration":761,"passed_time":0.5774578328,"remaining_time":0.1803608454},
{"learn":[3.404384724],"iteration":762,"passed_time":0.5779993578,"remaining_time":0.1795358425},
{"learn":[3.403041656],"iteration":763,"passed_time":0.5785414856,"remaining_time":0.1787117678},
{"learn":[3.401101731],"iteration":764,"passed_time":0.5790699214,"remaining_time":0.1778842242},
{"learn":[3.400890668],"iteration":765,"passed_time":0.5796128722,"remaining_time":0.1770618957},
{"learn":[3.399289941],"iteration":766,"passed_time":0.5801604866,"remaining_time":0.1762417124},
{"learn":[3.399202366],"iteration":767,"passed_time":0.5806842005,"remaining_time":0.1754150189},
{"learn":[3.397447845],"iteration":768,"passed_time":0.5812112969,"remaining_time":0.1745901295},
{"learn":[3.394655341],"iteration":769,"passed_time":0.5817434571,"remaining_time":0.1737675261},
{"learn":[3.393228229],"iteration":770,"passed_time":0.5822824289,"remaining_time":0.1729476994},
{"learn":[3.389691197],"iteration":771,"passed_time":0.5828202439,"remaining_time":0.1721282585},
{"learn":[3.389626772],"iteration":772,"passed_time":0.5833172142,"remaining_time":0.1712975519},
{"learn":[3.388480222],"iteration":773,"passed_time":0.5838437878,"remaining_time":0.1704763515},
{"learn":[3.388215066],"iteration":774,"passed_time":0.5843768471,"remaining_time":0.1696577943},
{"learn":[3.386324358],"iteration":775,"passed_time":0.5849044078,"remaining_time":0.1688383858},
{"learn":[3.383913061],"iteration":776,"passed_time":0.5854422124,"remaining_time":0.1680226684},
{"learn":[3.382839768],"iteration":777,"passed_time":0.5859816205,"remaining_time":0.1672081231},
{"learn":[3.381961844],"iteration":778,"passed_time":0.5865040598,"remaining_time":0.1663894701},
{"learn":[3.381521703],"iteration":779,"passed_time":0.5870297703,"remaining_time":0.1655724993},
{"learn":[3.380918963],"iteration":780,"passed_time":0.5875473307,"remaining_time":0.164753989},
{"learn":[3.377139006],"iteration":781,"passed_time":0.5880671479,"remaining_time":0.1639368776},
{"learn":[3.376004372],"iteration":782,"passed_time":0.5886073719,"remaining_time":0.163126181},
{"learn":[3.373826468],"iteration":783,"passed_time":0.5892182219,"remaining_time":0.1623356326},
{"learn":[3.373546786],"iteration":784,"passed_time":0.5897475961,"remaining_time":0.1615232269},
{"learn":[3.372109181],"iteration":785,"passed_time":0.5902838106,"remaining_time":0.1607134039},
{"learn":[3.370764924],"iteration":786,"passed_time":0.590815653,"remaining_time":0.1599030929},
{"learn":[3.367833107],"iteration":787,"passed_time":0.5913739023,"remaining_time":0.159100593},
{"learn":[3.36450404],"iteration":788,"passed_time":0.5919121976,"remaining_time":0.158293376},
{"learn":[3.361794558],"iteration":789,"passed_time":0.5924710909,"remaining_time":0.1574923153},
{"learn":[3.356880529],"iteration":790,"passed_time":0.5930263487,"remaining_time":0.1566909063},
{"learn":[3.353843509],"iteration":791,"passed_time":0.5935383472,"remaining_time":0.1558787579},
{"learn":[3.353640253],"iteration":792,"passed_time":0.5940405943,"remaining_time":0.155064821},
{"learn":[3.353055088],"iteration":793,"passed_time":0.5945413307,"remaining_time":0.1542512772},
{"learn":[3.351415617],"iteration":794,"passed_time":0.5950679323,"remaining_time":0.1534451901},
{"learn":[3.349169061],"iteration":795,"passed_time":0.5956110625,"remaining_time":0.1526440411},
{"learn":[3.346211014],"iteration":796,"passed_time":0.5961438552,"remaining_time":0.1518409067},
{"learn":[3.344560452],"iteration":797,"passed_time":0.5967124079,"remaining_time":0.1510475018},
{"learn":[3.344445461],"iteration":798,"passed_time":0.5972335494,"remaining_time":0.1502427327},
{"learn":[3.342608898],"iteration":799,"passed_time":0.5977727182,"remaining_time":0.1494431795},
{"learn":[3.339572899],"iteration":800,"passed_time":0.5983107821,"remaining_time":0.148644002},
{"learn":[3.339309302],"iteration":801,"passed_time":0.5988244331,"remaining_time":0.1478394486},
{"learn":[3.33698088],"iteration":802,"passed_time":0.5993581873,"remaining_time":0.1470405516},
{"learn":[3.334746342],"iteration":803,"passed_time":0.5998940856,"remaining_time":0.1462428368},
{"learn":[3.332048511],"iteration":804,"passed_time":0.6004108894,"remaining_time":0.1454411471},
{"learn":[3.331932544],"iteration":805,"passed_time":0.6009279726,"remaining_time":0.1446402316},
{"learn":[3.330541133],"iteration":806,"passed_time":0.6014810952,"remaining_time":0.1438486386},
{"learn":[3.329124989],"iteration":807,"passed_time":0.6020128871,"remaining_time":0.1430525672},
{"learn":[3.32583918],"iteration":808,"passed_time":0.6025605639,"remaining_time":0.1422608995},
{"learn":[3.325287299],"iteration":809,"passed_time":0.6030473978,"remaining_time":0.1414555624},
{"learn":[3.322745162],"iteration":810,"passed_time":0.6035730667,"remaining_time":0.1406600612},
{"learn":[3.319733662],"iteration":811,"passed_time":0.6041270675,"remaining_time":0.1398717841},
{"learn":[3.318080007],"iteration":812,"passed_time":0.6046840538,"remaining_time":0.1390847701},
{"learn":[3.317179538],"iteration":813,"passed_time":0.60522824,"remaining_time":0.1382953964},
{"learn":[3.315685949],"iteration":814,"passed_time":0.6057632616,"remaining_time":0.137504544},
{"learn":[3.314944576],"iteration":815,"passed_time":0.606269852,"remaining_time":0.1367079078},
{"learn":[3.312369052],"iteration":816,"passed_time":0.6068196313,"remaining_time":0.1359216555},
{"learn":[3.312321621],"iteration":817,"passed_time":0.6072361124,"remaining_time":0.1351063233},
{"learn":[3.309465776],"iteration":818,"passed_time":0.6077908138,"remaining_time":0.134322512},
{"learn":[3.308307377],"iteration":819,"passed_time":0.6083470956,"remaining_time":0.1335396063},
{"learn":[3.308076804],"iteration":820,"passed_time":0.6088695092,"remaining_time":0.1327498686},
{"learn":[3.305643326],"iteration":821,"passed_time":0.6094297344,"remaining_time":0.1319689692},
{"learn":[3.304154814],"iteration":822,"passed_time":0.6099668432,"remaining_time":0.1311836346},
{"learn":[3.303076321],"iteration":823,"passed_time":0.6104992372,"remaining_time":0.1303978953},
{"learn":[3.301746372],"iteration":824,"passed_time":0.6110215019,"remaining_time":0.1296106216},
{"learn":[3.301345455],"iteration":825,"passed_time":0.6115456713,"remaining_time":0.1288243908},
{"learn":[3.299181039],"iteration":826,"passed_time":0.6120665582,"remaining_time":0.1280381071},
{"learn":[3.297989357],"iteration":827,"passed_time":0.612597969,"remaining_time":0.1272546506},
{"learn":[3.294775182],"iteration":828,"passed_time":0.613140759,"remaining_time":0.1264741493},
{"learn":[3.293840636],"iteration":829,"passed_time":0.6136848851,"remaining_time":0.1256944945},
{"learn":[3.289279397],"iteration":830,"passed_time":0.6142218954,"remaining_time":0.1249139595},
{"learn":[3.286204979],"iteration":831,"passed_time":0.6147610634,"remaining_time":0.1241344455},
{"learn":[3.284833593],"iteration":832,"passed_time":0.6152935014,"remaining_time":0.1233541594},
{"learn":[3.283519914],"iteration":833,"passed_time":0.6158453054,"remaining_time":0.1225783222},
{"learn":[3.282853026],"iteration":834,"passed_time":0.6163832877,"remaining_time":0.1218002904},
{"learn":[3.281944673],"iteration":835,"passed_time":0.6169291387,"remaining_time":0.1210243765},
{"learn":[3.279764865],"iteration":836,"passed_time":0.6174702153,"remaining_time":0.1202480826},
{"learn":[3.277468839],"iteration":837,"passed_time":0.6180241433,"remaining_time":0.1194748344},
{"learn":[3.277124974],"iteration":838,"passed_time":0.6185608838,"remaining_time":0.1186988108},
{"learn":[3.275636037],"iteration":839,"passed_time":0.6191165755,"remaining_time":0.1179269668},
{"learn":[3.274413635],"iteration":840,"passed_time":0.619655388,"remaining_time":0.1171524455},
{"learn":[3.272636087],"iteration":841,"passed_time":0.620184815,"remaining_time":0.116376723},
{"learn":[3.269644466],"iteration":842,"passed_time":0.6207107641,"remaining_time":0.1156009371},
{"learn":[3.26852083],"iteration":843,"passed_time":0.6212441973,"remaining_time":0.1148271265},
{"learn":[3.267820927],"iteration":844,"passed_time":0.621774726,"remaining_time":0.1140533521},
{"learn":[3.267331099],"iteration":845,"passed_time":0.6222986511,"remaining_time":0.1132789507},
{"learn":[3.267231014],"iteration":846,"passed_time":0.6228360021,"remaining_time":0.1125075659},
{"learn":[3.267158695],"iteration":847,"passed_time":0.6233466572,"remaining_time":0.111731948},
{"learn":[3.264718705],"iteration":848,"passed_time":0.6238801497,"remaining_time":0.110961016},
{"learn":[3.261678512],"iteration":849,"passed_time":0.6244168061,"remaining_time":0.1101912011},
{"learn":[3.261368381],"iteration":850,"passed_time":0.6249225575,"remaining_time":0.109416523},
{"learn":[3.260128799],"iteration":851,"passed_time":0.6254742254,"remaining_time":0.1086504523},
{"learn":[3.258972952],"iteration":852,"passed_time":0.6259945943,"remaining_time":0.1078794905},
{"learn":[3.258724846],"iteration":853,"passed_time":0.6265317503,"remaining_time":0.1071119854},
{"learn":[3.25686724],"iteration":854,"passed_time":0.6270769156,"remaining_time":0.1063463775},
{"learn":[3.255750259],"iteration":855,"passed_time":0.627598206,"remaining_time":0.1055772683},
{"learn":[3.254915866],"iteration":856,"passed_time":0.6281202218,"remaining_time":0.1048088585},
{"learn":[3.254348625],"iteration":857,"passed_time":0.62864548,"remaining_time":0.1040415596},
{"learn":[3.253408514],"iteration":858,"passed_time":0.6291820075,"remaining_time":0.1032766741},
{"learn":[3.253291714],"iteration":859,"passed_time":0.6296826214,"remaining_time":0.1025064733},
{"learn":[3.250186342],"iteration":860,"passed_time":0.6302132093,"remaining_time":0.1017417376},
{"learn":[3.249141318],"iteration":861,"passed_time":0.6307673958,"remaining_time":0.1009813232},
{"learn":[3.246300388],"iteration":862,"passed_time":0.6313071202,"remaining_time":0.1002190909},
{"learn":[3.245205135],"iteration":863,"passed_time":0.6318563614,"remaining_time":0.09945887171},
{"learn":[3.244403535],"iteration":864,"passed_time":0.6323915512,"remaining_time":0.09869694729},
{"learn":[3.244211781],"iteration":865,"passed_time":0.6329206043,"remaining_time":0.09793459696},
{"learn":[3.242286347],"iteration":866,"passed_time":0.6334547941,"remaining_time":0.09717357279},
{"learn":[3.239606746],"iteration":867,"passed_time":0.6340102752,"remaining_time":0.09641630913},
{"learn":[3.236773361],"iteration":868,"passed_time":0.6345776718,"remaining_time":0.09566130611},
{"learn":[3.234552446],"iteration":869,"passed_time":0.6351206979,"remaining_time":0.09490309279},
{"learn":[3.233724647],"iteration":870,"passed_time":0.6356566186,"remaining_time":0.09414432124},
{"learn":[3.230851485],"iteration":871,"passed_time":0.636202374,"remaining_time":0.09338750444},
{"learn":[3.227728941],"iteration":872,"passed_time":0.636739289,"remaining_time":0.09262988512},
{"learn":[3.225787575],"iteration":873,"passed_time":0.6372758943,"remaining_time":0.09187272618},
{"learn":[3.222797487],"iteration":874,"passed_time":0.6378202758,"remaining_time":0.09111718226},
{"learn":[3.22137014],"iteration":875,"passed_time":0.6383707908,"remaining_time":0.09036298865},
{"learn":[3.219701963],"iteration":876,"passed_time":0.638919775,"remaining_time":0.08960904484},
{"learn":[3.21783327],"iteration":877,"passed_time":0.6394530385,"remaining_time":0.08885338348},
{"learn":[3.217713355],"iteration":878,"passed_time":0.639967097,"remaining_time":0.08809558445},
{"learn":[3.217666091],"iteration":879,"passed_time":0.6404703377,"remaining_time":0.08733686423},
{"learn":[3.214962005],"iteration":880,"passed_time":0.6410048125,"remaining_time":0.08658294289},
{"learn":[3.214081828],"iteration":881,"passed_time":0.641549278,"remaining_time":0.08583085579},
{"learn":[3.213358337],"iteration":882,"passed_time":0.6420743705,"remaining_time":0.08507667197},
{"learn":[3.210850401],"iteration":883,"passed_time":0.6426072225,"remaining_time":0.08432402467},
{"learn":[3.207810328],"iteration":884,"passed_time":0.6431333998,"remaining_time":0.08357100675},
{"learn":[3.204935073],"iteration":885,"passed_time":0.6436672365,"remaining_time":0.08281948641},
{"learn":[3.20280198],"iteration":886,"passed_time":0.6442299303,"remaining_time":0.08207213318},
{"learn":[3.200663495],"iteration":887,"passed_time":0.6447673474,"remaining_time":0.08132200778},
{"learn":[3.197301669],"iteration":888,"passed_time":0.6453138561,"remaining_time":0.0805734961},
{"learn":[3.195666943],"iteration":889,"passed_time":0.6458484542,"remaining_time":0.07982396625},
{"learn":[3.193886506],"iteration":890,"passed_time":0.6463713706,"remaining_time":0.07907348979},
{"learn":[3.190601248],"iteration":891,"passed_time":0.6469012139,"remaining_time":0.07832436222},
{"learn":[3.188983797],"iteration":892,"passed_time":0.6474344886,"remaining_time":0.07757613693},
{"learn":[3.187365749],"iteration":893,"passed_time":0.6479778005,"remaining_time":0.07682958261},
{"learn":[3.186160771],"iteration":894,"passed_time":0.6485097214,"remaining_time":0.07608214608},
{"learn":[3.185358981],"iteration":895,"passed_time":0.6490385351,"remaining_time":0.07533482997},
{"learn":[3.183832164],"iteration":896,"passed_time":0.6495747488,"remaining_time":0.07458885076},
{"learn":[3.183106966],"iteration":897,"passed_time":0.6501223704,"remaining_time":0.0738446345},
{"learn":[3.182838152],"iteration":898,"passed_time":0.6506780029,"remaining_time":0.07310175561},
{"learn":[3.180835453],"iteration":899,"passed_time":0.6512898396,"remaining_time":0.07236553774},
{"learn":[3.179957348],"iteration":900,"passed_time":0.651818518,"remaining_time":0.0716204587},
{"learn":[3.179752966],"iteration":901,"passed_time":0.6523407788,"remaining_time":0.07087516222},
{"learn":[3.178851983],"iteration":902,"passed_time":0.6528716484,"remaining_time":0.07013128449},
{"learn":[3.176748586],"iteration":903,"passed_time":0.6533985727,"remaining_time":0.06938745905},
{"learn":[3.172960988],"iteration":904,"passed_time":0.6539403426,"remaining_time":0.06864567133},
{"learn":[3.172794225],"iteration":905,"passed_time":0.6544329456,"remaining_time":0.06789922394},
{"learn":[3.169996507],"iteration":906,"passed_time":0.6549611413,"remaining_time":0.06715698582},
{"learn":[3.16813015],"iteration":907,"passed_time":0.65550498,"remaining_time":0.06641680414},
{"learn":[3.166920871],"iteration":908,"passed_time":0.6560435851,"remaining_time":0.06567653052},
{"learn":[3.16531606],"iteration":909,"passed_time":0.6565813576,"remaining_time":0.06493661779},
{"learn":[3.162035247],"iteration":910,"passed_time":0.6571193535,"remaining_time":0.06419717065},
{"learn":[3.16189467],"iteration":911,"passed_time":0.6576071464,"remaining_time":0.06345332115},
{"learn":[3.161008416],"iteration":912,"passed_time":0.6581485337,"remaining_time":0.06271513957},
{"learn":[3.160560787],"iteration":913,"passed_time":0.6586934524,"remaining_time":0.06197772091},
{"learn":[3.160416261],"iteration":914,"passed_time":0.6592178155,"remaining_time":0.06123881347},
{"learn":[3.15844291],"iteration":915,"passed_time":0.6597602908,"remaining_time":0.0605020354},
{"learn":[3.155040501],"iteration":916,"passed_time":0.6603057588,"remaining_time":0.05976595199},
{"learn":[3.154937548],"iteration":917,"passed_time":0.6608206387,"remaining_time":0.0590275516},
{"learn":[3.153721161],"iteration":918,"passed_time":0.6613531888,"remaining_time":0.0582911951},
{"learn":[3.153170511],"iteration":919,"passed_time":0.6618845277,"remaining_time":0.05755517632},
{"learn":[3.153113601],"iteration":920,"passed_time":0.6623867708,"remaining_time":0.05681710629},
{"learn":[3.150607379],"iteration":921,"passed_time":0.6629219181,"remaining_time":0.05608233147},
{"learn":[3.148408359],"iteration":922,"passed_time":0.6634511457,"remaining_time":0.05534749536},
{"learn":[3.147495728],"iteration":923,"passed_time":0.6639871825,"remaining_time":0.05461366436},
{"learn":[3.146946235],"iteration":924,"passed_time":0.6645102726,"remaining_time":0.0538792113},
{"learn":[3.14472738],"iteration":925,"passed_time":0.6650682765,"remaining_time":0.05314800482},
{"learn":[3.144469477],"iteration":926,"passed_time":0.665580765,"remaining_time":0.05241358775},
{"learn":[3.142975516],"iteration":927,"passed_time":0.6661133864,"remaining_time":0.05168121101},
{"learn":[3.14079113],"iteration":928,"passed_time":0.6666437093,"remaining_time":0.05094908865},
{"learn":[3.138173032],"iteration":929,"passed_time":0.6671674239,"remaining_time":0.05021690287},
{"learn":[3.136352813],"iteration":930,"passed_time":0.6676946628,"remaining_time":0.04948542614},
{"learn":[3.133735004],"iteration":931,"passed_time":0.6682312304,"remaining_time":0.04875506831},
{"learn":[3.1319496],"iteration":932,"passed_time":0.6687687507,"remaining_time":0.04802519432},
{"learn":[3.129865343],"iteration":933,"passed_time":0.669295687,"remaining_time":0.0472949843},
{"learn":[3.129830206],"iteration":934,"passed_time":0.6696805009,"remaining_time":0.04655532894},
{"learn":[3.126676562],"iteration":935,"passed_time":0.6702307004,"remaining_time":0.0458277402},
{"learn":[3.12645665],"iteration":936,"passed_time":0.670750159,"remaining_time":0.0450984632},
{"learn":[3.126378007],"iteration":937,"passed_time":0.6712610583,"remaining_time":0.04436906782},
{"learn":[3.124621914],"iteration":938,"passed_time":0.6717990326,"remaining_time":0.04364189669},
{"learn":[3.123379018],"iteration":939,"passed_time":0.6723408177,"remaining_time":0.04291537135},
{"learn":[3.123332451],"iteration":940,"passed_time":0.6729325849,"remaining_time":0.04219237248},
{"learn":[3.122432444],"iteration":941,"passed_time":0.6736416259,"remaining_time":0.04147687293},
{"learn":[3.121889006],"iteration":942,"passed_time":0.6742597314,"remaining_time":0.04075589045},
{"learn":[3.121070914],"iteration":943,"passed_time":0.6748716963,"remaining_time":0.04003476164},
{"learn":[3.118444705],"iteration":944,"passed_time":0.6754950706,"remaining_time":0.03931452792},
{"learn":[3.116820458],"iteration":945,"passed_time":0.6760421662,"remaining_time":0.03859014479},
{"learn":[3.114971041],"iteration":946,"passed_time":0.6765880104,"remaining_time":0.03786606605},
{"learn":[3.114685138],"iteration":947,"passed_time":0.6771188953,"remaining_time":0.03714154278},
{"learn":[3.113399363],"iteration":948,"passed_time":0.6776641911,"remaining_time":0.03641820205},
{"learn":[3.110575399],"iteration":949,"passed_time":0.6782222775,"remaining_time":0.03569590934},
{"learn":[3.110466553],"iteration":950,"passed_time":0.6787187746,"remaining_time":0.0349707886},
{"learn":[3.108691641],"iteration":951,"passed_time":0.6792611458,"remaining_time":0.03424846113},
{"learn":[3.107898017],"iteration":952,"passed_time":0.6797841903,"remaining_time":0.03352555818},
{"learn":[3.105551729],"iteration":953,"passed_time":0.680321625,"remaining_time":0.03280376808},
{"learn":[3.104824945],"iteration":954,"passed_time":0.6808465469,"remaining_time":0.03208177446},
{"learn":[3.103186704],"iteration":955,"passed_time":0.6814025749,"remaining_time":0.03136162479},
{"learn":[3.102330655],"iteration":956,"passed_time":0.6819425547,"remaining_time":0.03064109702},
{"learn":[3.102291298],"iteration":957,"passed_time":0.6824370599,"remaining_time":0.02991895252},
{"learn":[3.100363529],"iteration":958,"passed_time":0.6829688999,"remaining_time":0.02919887893},
{"learn":[3.097871596],"iteration":959,"passed_time":0.6835090759,"remaining_time":0.02847954483},
{"learn":[3.097372213],"iteration":960,"passed_time":0.6840184428,"remaining_time":0.02775933327},
{"learn":[3.095981813],"iteration":961,"passed_time":0.6845473406,"remaining_time":0.02704033154},
{"learn":[3.095347452],"iteration":962,"passed_time":0.6850793239,"remaining_time":0.02632184318},
{"learn":[3.094728409],"iteration":963,"passed_time":0.6856288389,"remaining_time":0.02560439647},
{"learn":[3.094118537],"iteration":964,"passed_time":0.6861518794,"remaining_time":0.02488633759},
{"learn":[3.093793695],"iteration":965,"passed_time":0.68666658,"remaining_time":0.02416838894},
{"learn":[3.092581602],"iteration":966,"passed_time":0.6871971134,"remaining_time":0.02345140097},
{"learn":[3.091694202],"iteration":967,"passed_time":0.6877514093,"remaining_time":0.02273558378},
{"learn":[3.090298312],"iteration":968,"passed_time":0.6882800925,"remaining_time":0.02201928056},
{"learn":[3.090020107],"iteration":969,"passed_time":0.6888175695,"remaining_time":0.02130363617},
{"learn":[3.088949869],"iteration":970,"passed_time":0.6893321388,"remaining_time":0.02058767459},
{"learn":[3.086700204],"iteration":971,"passed_time":0.6898647354,"remaining_time":0.0198726467},
{"learn":[3.086584317],"iteration":972,"passed_time":0.6903900881,"remaining_time":0.01915779278},
{"learn":[3.084850742],"iteration":973,"passed_time":0.6909188601,"remaining_time":0.01844341926},
{"learn":[3.084239948],"iteration":974,"passed_time":0.6914348297,"remaining_time":0.0177290982},
{"learn":[3.082561673],"iteration":975,"passed_time":0.6919817884,"remaining_time":0.01701594562},
{"learn":[3.07991814],"iteration":976,"passed_time":0.6925144402,"remaining_time":0.01630279644},
{"learn":[3.079350277],"iteration":977,"passed_time":0.6930366985,"remaining_time":0.01558978258},
{"learn":[3.077637462],"iteration":978,"passed_time":0.6935913014,"remaining_time":0.01487785223},
{"learn":[3.076733301],"iteration":979,"passed_time":0.6941286924,"remaining_time":0.01416589168},
{"learn":[3.07594065],"iteration":980,"passed_time":0.6946578736,"remaining_time":0.01345412803},
{"learn":[3.072594655],"iteration":981,"passed_time":0.6952021719,"remaining_time":0.01274301333},
{"learn":[3.071977674],"iteration":982,"passed_time":0.6957606737,"remaining_time":0.01203248368},
{"learn":[3.069532634],"iteration":983,"passed_time":0.696284675,"remaining_time":0.01132170203},
{"learn":[3.068870784],"iteration":984,"passed_time":0.6968103399,"remaining_time":0.01061132497},
{"learn":[3.068801463],"iteration":985,"passed_time":0.6973014121,"remaining_time":0.009900831409},
{"learn":[3.067433249],"iteration":986,"passed_time":0.6978554746,"remaining_time":0.009191612127},
{"learn":[3.065611456],"iteration":987,"passed_time":0.6983856389,"remaining_time":0.008482416667},
{"learn":[3.063039162],"iteration":988,"passed_time":0.6989293551,"remaining_time":0.00777373398},
{"learn":[3.06177873],"iteration":989,"passed_time":0.6994706991,"remaining_time":0.007065360597},
{"learn":[3.061689148],"iteration":990,"passed_time":0.6999670162,"remaining_time":0.006356915384},
{"learn":[3.058984039],"iteration":991,"passed_time":0.7005195086,"remaining_time":0.005649350876},
{"learn":[3.057492984],"iteration":992,"passed_time":0.7010751936,"remaining_time":0.004942121203},
{"learn":[3.057290731],"iteration":993,"passed_time":0.7015971316,"remaining_time":0.004234992746},
{"learn":[3.056068348],"iteration":994,"passed_time":0.7021040151,"remaining_time":0.00352816088},
{"learn":[3.054987307],"iteration":995,"passed_time":0.702637558,"remaining_time":0.002821837582},
{"learn":[3.054200234],"iteration":996,"passed_time":0.7031862764,"remaining_time":0.002115906549},
{"learn":[3.052732869],"iteration":997,"passed_time":0.7037346674,"remaining_time":0.001410289915},
{"learn":[3.051787862],"iteration":998,"passed_time":0.7042908379,"remaining_time":0.0007049958337},
{"learn":[3.051366222],"iteration":999,"passed_time":0.7048240381,"remaining_time":0}
]}